{
  "ts": "2025-10-04T19:06:28.758744+00:00",
  "run_id": "ui_default",
  "qid": "q_1759604770841_00bd61",
  "query": "Create me a new recipe which is a mix of many recipes",
  "context": "\n-----Backgrounds-----\n```csv\n\"id\",\t\"content\"\n0,\t\"# Indian Cuisine Recipes Featuring Garlic and Onion  This community focuses on a variety of Indian recipes, notably those that utilize garlic and onion as foundational ingredients. Key dishes include Dal Shorba, Kaju Butter Masala, and Waffled Falafels and Vegetables, which highlight the importance of these aromatics in enhancing flavors. The interdependence of these dishes is illustrated through shared ingredients, methods, and regional variations, demonstrating a rich cultural heritage.  ## Core ingredients: Garlic and Onion  Garlic and onion are essential components across this community's recipes, serving as aromatics that significantly enhance flavor. These ingredients are foundational to many Indian cuisines and are crucial in the preparation methods typical of the region, such as sautéing, which forms the flavor base for various dishes.  ## Diversity of recipes representing Indian cuisine  The community encompasses a range of Indian culinary styles, illustrated by dishes such as Goan Style Mushroom Vindaloo and Kashmiri Style Rista, each reflecting regional flavors and cooking techniques. The recipes leverage the unique flavor properties of garlic and onion to achieve deep and complex taste profiles characteristic of Indian cooking traditions.  ## Dietary inclusivity with vegetarian options  Several recipes cater to vegetarian diets, showcasing dishes such as Waffled Falafels and Vegetables, Kaju Butter Masala, and soups like Dal Shorba. This dietary consideration enhances the community's relevance to a broader audience, promoting nutritious and diverse meal choices.  ## Interconnected use of ingredients  Relationships reveal interactions between garlic and onion with other ingredients such as cumin, tomatoes, and various spices in recipes. For instance, sauces may combine garlic and onion for a complex flavor backdrop, thereby enriching the overall dish aesthetic and taste.  ## Common cooking methods highlight procedural complexity  The community exhibits a variety of cooking methods including sautéing, simmering, and pressure cooking. Sautéing is frequently employed to prepare garlic and onion, illustrating its importance in building flavor bases for dishes like Kaju Butter Masala and Dal Shorba.  ## Health benefits associated with garlic and onion  Numerous health benefits attributed to garlic and onion, such as anti-inflammatory and antioxidant properties, enhance the appeal of these recipes. Their frequent incorporation not only boosts flavor but also emphasizes overall well-being, positioning the community as not just culinary but also health-oriented.  ## Clear categorization aids in recipe navigation  The recipes are well-categorized by type (e.g., soups, curries) and dietary labels, making it easier for cooks to navigate and select meals based on personal preferences or dietary restrictions. This organization underscores the diversity present in achieving varied culinary outcomes.  ## Cultural significance of meal preparation practices  These recipes often reflect cultural practices surrounding meal preparation, making garlic and onion integral to both festive and daily cooking in Indian households. The connection of these ingredients to traditional practices highlights the cultural richness and adaptability of Indian cuisine.  ## Explicit timing for preparation and cooking  Cooking times for various dishes such as Dal Shorba (10-15 minutes preparation) provide essential scheduling information for cooks, crucial for effective meal planning. Clear timing guidelines foster efficient kitchen management, especially in professional settings.\"\n1,\t\"# Bengali Vegetarian Dishes Featuring Turmeric and Salt  This community features a range of Bengali vegetarian recipes centered around key ingredients such as turmeric powder and salt. Significant entities include popular dishes like 'Bengali Style Kaddu Lobia Ki Sabzi with Panch Phoran Masala' and 'Arbi Jhol'. The relationships highlight the fundamental role of these ingredients in seasoning, flavor enhancement, and the methods of preparation involved in these culturally rich recipes.  ## Core vegetarian recipes with health benefits  The community showcases recipes like 'Bengali Style Kaddu Lobia Ki Sabzi with Panch Phoran Masala' and 'Arbi Jhol', distinguished by their plant-based ingredients. Turmeric powder is a recurring element in these dishes, noted for its health benefits, including its anti-inflammatory properties. Salt is essential as a basic seasoning, used to enhance flavors in almost every recipe, emphasizing its necessity in cooking.  ## Significance of turmeric as a key spice  Turmeric powder (Haldi) plays a vital role across various recipes, such as adding color and depth of flavor to dishes like 'Arbi Jhol'. It is recognized not just for its culinary value but also for its health-enhancing characteristics. Relationships show that turmeric is commonly paired with other spices, which adds both complexity and health benefits, establishing its central role in Bengali vegetarian cooking.  ## Salt's ubiquitous role in flavor enhancement  Throughout the narratives of the recipes, salt is a consistent ingredient required for seasoning. For dishes like 'Bengali Aloo Dum', salt is critical for achieving the proper flavor balance. Additionally, the community outlines various substitutions for salt, suggesting places where lower-sodium options can be used, which reflects a growing concern for health-conscious cooking.  ## Diverse cooking methods showcased  The preparation of these recipes involves various cooking techniques including pressure cooking and sautéing. For instance, dishes like 'Arbi Jhol' utilize pressure cooking to ensure the softness and flavor integration of colocasia. These methods not only enhance the flavor profiles but also cater to the texture preferences typical of Bengali cuisine.  ## Explicit time constraints guide meal planning  Most recipes provide clear preparation and cooking times that enable effective meal planning. For example, 'Bengali Style Kaddu Lobia Ki Sabzi' has a designated prep time of 10 minutes, which helps cooks to streamline their culinary tasks. Incorporating time indicators aids novice cooks in managing their cooking schedules efficiently and accurately.  ## Cultural significance of recipes  The recipes within this community reflect deep-rooted cultural practices and the importance of traditional vegetarian cuisine in Bengali culture. By focusing on dishes that utilize local and seasonal ingredients like pumpkin and black-eyed beans, these recipes emphasize cultural heritage while promoting inclusive dietary options.  ## Dietary classifications support vegetarian practices  Many dishes are classified as vegetarian, making them suitable for those adhering strictly to plant-based diets. Labels of 'vegetarian' or explicit references to dietary guidelines help consumers make informed choices, showcasing the community's commitment to catering to diverse dietary preferences.\"\n2,\t\"# Diverse Indian Curry Recipes Featuring Green Chillies  This community encapsulates a variety of Indian curry recipes that prominently feature green chillies as a key ingredient. Significant entities include several regional recipes such as Kerala Style Mutton Pepper Fry, Bengali Aloo Dum, Coorg Style Kumbala Curry, and Malwani Pumpkin and Raw Mango Curry. Key relationships highlight the usage of ingredients, methods of cooking, preparation and cooking times, as well as dietary classifications.  ## Variety of Recipes Representing Different Regions  The community consists of an array of dishes rooted in various Indian cuisines, including Kerala, Bengali, Coorg, and Malvani. Notable recipes include Kerala Style Mutton Pepper Fry, which features mutton and spices, and Bengali Aloo Dum, focusing on baby potatoes and spices. Each recipe represents the unique features and flavors associated with its regional culinary tradition.  ## Green Chillies as a Central Ingredient  Green chillies are a common ingredient across multiple recipes, known for providing heat and enhancing flavor. They are featured in recipes like Green Chilli Vegetable and many curry preparations where they serve as the primary source of spice. Their widespread use emphasizes the importance of balancing heat in these dishes to cater to different palates.  ## Specific Preparation and Cooking Times  Several recipes specify their preparation and cooking times, ensuring that cooks can plan accordingly. For example, the preparation for Kerala Style Mutton Pepper Fry requires 10 minutes, while cooking takes around 50 minutes. These explicit time frames guide the cooking process effectively, making it easier to manage multiple dishes simultaneously.  ## Dietary Classifications and Suitability  Many of the recipes are categorized as vegetarian or non-vegetarian, catering to diverse dietary needs. Dishes like Coorg Style Kumbala Curry and Dahi Wale Tinda Ki Sabzi are classified as vegetarian, while Kerala Style Mutton Pepper Fry is a non-vegetarian dish, allowing users to choose based on their dietary preferences.  ## Common Usage of Salt in Flavors  Salt appears consistently in the recipes, identified as a crucial element for flavor enhancement. For instance, it is necessary in Bengali Aloo Dum and Kerala Style Mutton Pepper Fry. The relationships establish a recurring requirement for salt to ensure that the dishes achieve appropriate taste profiles.  ## Cooking Techniques and Methods  The methodologies adopted in these recipes vary from sautéing and cooking to grinding spices. Techniques like 'Heat' and 'Stir' are fundamental in preparing these dishes, reflecting general cooking methodologies commonly used across Indian recipes. The importance of these methods is evident in how they influence the texture and flavor of the final dish.  ## Ingredients and Complementary Spices  The recipes share a variety of ingredients that enhance their profiles, including turmeric, garlic, and various spices like fennel and coriander. These spices not only complement the green chillies but also reinforce the culinary tradition of layering flavors within these dishes, showcasing the complexity of Indian cuisine.  ## Tools and Appliances Used  Different recipes highlight the tools required for preparation and cooking, such as non-stick woks, kadais, and heavy-bottomed pans used in these curries. The choice of cooking equipment plays a significant role in the cooking technique and helps achieve desired results, ensuring better management of heat when preparing dishes.  ## Serving Suggestions and Accompaniments  Many recipes include serving suggestions, such as pairing with rice or chapati. For instance, dishes like Cucumber Mor Kuzhambu are suggested to be served with steamed rice, providing guidance on how best to enjoy the flavors. This aspect enriches the dining experience by complementing the main dishes.\"\n3,\t\"# Kerala Style Mutton Pepper Fry — Mutton Recipe  This community centers around the 'Kerala Style Mutton Pepper Fry' recipe, highlighting key ingredients like mutton and a diverse range of spices. It employs essential cooking methods including marinating and frying, with explicit mentions of preparation and cooking times. Furthermore, it identifies the dish as a part of both Kerala recipes and as a non-vegetarian appetizer.  ## Core ingredients and spices  The recipe prominently features mutton as the main ingredient, supplemented by a rich mix of spices including garlic, ginger, turmeric, and red chili powder. Their inclusion is critical for flavor development and showcases the traditional essence of Kerala cuisine.  ## Methodology of preparation  This dish involves essential cooking steps: marinating the mutton with spices and frying the mixture. The act of marinating ensures that the flavors deeply penetrate the meat, while frying is integral to create a desirable texture and aroma.  ## Preparation and cooking time specifications  The recipe outlines 'Preparation Time: 10 minutes' and 'Cooking Time: 60 minutes.' This structured time allocation is significant for cooks to manage their cooking process effectively and ensure the dish is prepared within the expected timeframe.  ## Non-vegetarian classification and serving style  The dish is categorized as a non-vegetarian appetizer, which holds cultural significance within Kerala cuisine. This classification informs cooks about its position within meal planning and dietary preferences.  ## Diverse cooking techniques employed  Techniques such as frying and mixing play a crucial role in the cooking process. Effective frying is necessary to enhance flavors and achieve proper doneness, while thorough mixing of ingredients ensures even seasoning and texture.\"\n4,\t\"# Broccoli-Centric Recipes — Vegetarian Cuisine  This community revolves around recipes primarily involving broccoli, including soups and stir-fries. Key entities include various broccoli-based recipes, associated ingredients like paneer and horse gram, and various cooking tools like woks and soup pots. The overarching dietary theme is vegetarianism, with clear emphasis on nutrition, preparation times, and cooking methods.  ## Key Recipes Highlighted  The community includes notable recipes such as 'Protein Rich Paneer and Horse Gram Soup', 'Light and Creamy Broccoli Soup', and 'Chinese Style Sweet and Spicy Broccoli Stir Fry with Sausage'. Each recipe emphasizes various cooking methods and ingredients, suggesting a diverse culinary approach focusing on the nutritional benefits of broccoli.  ## Diverse Ingredient Profiles  The recipes incorporate a rich array of ingredients including broccoli, mixed vegetables, paneer, and various spices. Broccoli serves as a foundational element across different dishes, while complementary ingredients like horse gram dal and paneer enhance protein content in vegetarian meals.  ## Emphasis on Preparation and Cooking Times  Each recipe comes with specified preparation and cooking times, as seen in 'Chinese Style Sweet and Spicy Broccoli Stir Fry with Sausage' which has a labeled prep time of 10 minutes, indicating a focus on efficient meal preparation for cooks.  ## Vegetarian Dietary Compliance  The recipes are predominately vegetarian, as evidenced by the 'method-for' relationships stating that the 'Light and Creamy Broccoli Soup' adheres to vegetarian dietary requirements. This aligns well with the community's theme of promoting health-conscious cooking.  ## Cooking Techniques and Tool Utilization  Various cooking techniques such as sautéing, steaming, and using pressure cookers are prevalent in the recipes. Tools like the non-stick pan, soup pot, and handy traditional vessels enhance cooking versatility, indicating the importance of methodical preparation in achieving texture and flavor.  ## Nutritional Value Focus  Broccoli serves not only as the primary ingredient but as a nutritional keystone throughout the recipes. The incorporation of high-protein ingredients alongside broccoli highlights a conscious effort to bolster the nutritional profile of vegetarian meals for optimal health benefits.  ## Regional and Culinary Influences  The community includes recipes that draw from various culinary influences such as Indian and Chinese cuisines, seen in dishes like 'Chinese Style Sweet and Spicy Broccoli Stir Fry'. This mix showcases the versatility of broccoli in diverse recipes while adding complexity to the community’s culinary identity.  ## Seasoning and Flavoring Complexity  The use of various spices including turmeric, garlic, and chili powders indicates a layered approach to flavoring the dishes. Seasoning ingredients enhance the taste profile, contributing to the unique appeal of each recipe while enhancing the overall sensory experience.  ## Role of Mixed Vegetables  Several recipes feature mixed vegetables, which enrich the nutritional value and flavor profile of the primary broccoli dishes. This approach not only adds variety but also appeals to a broader range of dietary preferences, creating meals that are both colorful and nutritious.\"\n5,\t\"# Steamed Chicken with Salad (Continental, Appetizer)  This community revolves around a dish of steamed chicken served with a fresh salad, incorporating a variety of ingredients like vegetables and dressings. Key relationships include the use of a vegetable steamer for preparation and the categorization of the dish under continental cuisine and as an appetizer. Notable ingredients consumed are chicken breasts, various vegetables, and seasonings, with explicit preparation and cooking time noted.  ## Core dish composition and method  The recipe consists of steamed chicken breasts served alongside a mixed vegetable salad. It highlights both the steaming technique and the combination of fresh ingredients that enhance flavor, showing a clear link between the use of the vegetable steamer and the meal's preparation.  ## Ingredients and tools involved  Key ingredients include chicken breasts for the protein, various salad vegetables such as cabbage, carrots, and red bell peppers, and additional flavoring components like coriander leaves and olive oil. The vegetable steamer is essential for preparing the chicken and vegetables, emphasizing the need for proper tool usage in the cooking process.  ## Diet and cuisine classification  The dish is categorized under continental cuisine and categorized as an appetizer. It fits within the high-protein non-vegetarian diet category, highlighting its appeal to specific dietary preferences and its versatile serving options.  ## Explicit time constraints for preparation and cooking  Preparation time is noted as 10 minutes, while cooking takes about 30 minutes. These time constraints help in planning and executing the dish effectively, ensuring that cooks are aware of the total time commitment required for meal preparation.  ## Versatile use of seasonings and dressings  The dish utilizes several seasonings and dressings, such as salt, pepper, and fresh orange juice, contributing to a flavorful experience. The use of these ingredients is critical for enhancing the overall taste of the dish while also providing different health benefits.\"\n6,\t\"# Vegetarian Global Cuisine: Smoked Spanish Rice & Varied Salads  This community encompasses several vegetarian recipes, highlighting the Smoked Vegetarian Spanish Rice as a central dish. It incorporates key ingredients such as red bell pepper, cabbage, and basmati rice, along with various methods and tools. Its relationships indicate the dietary suitability (vegetarian), preparation durations, and notable cooking techniques, such as smoking. Recipes range from appetizers to main courses, each with specific ingredient interactions and preparation instructions.  ## Diverse range of vegetarian recipes  The community includes varied vegetarian recipes such as Smoked Vegetarian Spanish Rice, Cabbage, Bell Pepper and Apples with Sriracha Slaw, and Steamed Chicken with Salad. Each recipe presents unique combinations of ingredients and preparation techniques suitable for vegetarian diets, emphasizing the versatility of fruits, vegetables, and grains.  ## Key ingredients with significant culinary roles  Ingredients like red bell pepper, basmati rice, and cabbage are integral to multiple recipes. Red bell pepper appears prominently as a sweetening and colorful agent in dishes like Slaw and Spanish Rice. Basmati rice serves as a foundational element in recipes including the vegetarian Spanish rice, highlighting its role in various cuisines.  ## Explicit time constraints for recipes  Preparation and cooking durations are specified for several recipes, such as 10 minutes preparation time and 30 minutes cooking time for Smoked Vegetarian Spanish Rice. These time entities are critical for planning cooking sessions and managing schedules for meal preparation.  ## Cooking methods that enhance flavor  The use of unique methods such as smoking, sautéing, and steaming are prevalent across the recipes. For instance, Smoked Vegetarian Spanish Rice employs the smoking method to infuse it with smokiness, while the slaw utilizes sautéing to highlight flavor enhancement with ingredients like garlic and onions.  ## Varied nutritional profiles across dishes  The inclusion of diverse ingredients in the recipes ensures a broad range of nutrients. For example, the rice dish incorporates vegetables and spices, while the salads add protein sources through items like chickpeas, showcasing the community's ability to cater to nutritional needs.  ## Labeling and dietary suitability highlighted  Several recipes are explicitly labeled as 'vegetarian,' underlining their suitability for vegetarian diets. For instance, the Smoked Vegetarian Spanish Rice and the Cabbage, Bell Pepper and Apples with Sriracha Slaw are confirmed vegetarians, aligning these recipes with dietary claims.  ## Tools and equipment essential for preparation  Key tools such as bowls, pans, and a vegetable steamer are necessary for executing the recipes. For instance, the bowl is crucial for mixing ingredients in various salads and dressings, indicating the communal nature of preparing these dishes and the importance of having the right kitchenware.  ## Cross-referencing with cultural cuisines  The dishes reflect a blend of cultural influences, such as the Spanish traditional aspects seen in the smoked rice and the modern interpretations present in the slaw. The categorization under the 'world recipes' and 'continental' further elaborates on the community's diverse culinary landscape.\"\n7,\t\"# Vegetable Mix Community — Nutrition and Flavor  The community focuses on mixed vegetables and their connections with various recipes and ingredients. The key ingredients include carrot, beans, cauliflower, lauki, and white pumpkin, all of which contribute to a variety of dishes. The relationships reveal that these vegetables are often utilized together in meals, providing nutrition and enhancing flavor.  ## Diverse ingredient usage  Mixed vegetables consist of a variety of chopped vegetables, which are integral to numerous recipes, including 'Tuna Rasam Bhaji', 'Goan Vegetable Curry', and 'Mulakootal'. This indicates a versatile usage across different cuisines, providing nutritional value and variety.  ## Key vegetable relationships  Among the mixed vegetables, components like carrots and beans are noted for their specific contributions to dishes. Carrots add sweetness and crunch, while beans contribute texture and nutrition. The relationships show how these fundamental ingredients work together in many recipes.  ## Common usage in signature dishes  Mixed vegetables are featured prominently in several dishes like 'Vegetarian Sago Dumpling' and 'Moroccan Harira', indicating their role in providing essential flavors and components. Recipes that utilize mixed vegetables capitalize on their combined textures and tastes to enhance overall dish quality.  ## Cooking methods  Several relationships highlight that mixed vegetables are often steamed, as indicated by their connection to the 'Vegetable Steamer'. This method preserves nutrients while ensuring the vegetables are cooked to an appropriate tenderness for consumption.  ## Flavor-enhancing ingredients  The addition of flavorings such as turmeric powder, lemon juice, and dried oregano alongside mixed vegetables amplifies the overall taste profile of dishes. This emphasizes the importance of seasoning in the culinary context of mixed vegetables.\"\n```\n-----Reasoning Path-----\n```csv\n\"id\",\t\"source\",\t\"target\",\t\"description\",\t\"weight\",\t\"rank\"\n0,\t\"INDIAN\",\t\"SALT\",\t\"is-labeled-as: Salt is a basic ingredient in Indian cooking, essential for flavor.\"<\",\t7.5,\t693\n1,\t\"MIXED VEGETABLE HANDI\",\t\"SALT\",\t\"requires: The recipe requires salt for seasoning.\",\t9.0,\t559\n2,\t\"SALT\",\t\"SPICY PRESSURE COOKER MUTTON CURRY\",\t\"consumes: Salt is used to enhance the flavor of the mutton.\",\t8.0,\t550\n3,\t\"KERALA STYLE MUTTON PEPPER FRY\",\t\"SALT\",\t\"consumes: Salt is used to enhance the flavors during cooking.\"<SEP>\"substitutes-for: Salt is also mentioned twice, but as a general ingredient, it's still relevant.\",\t12.0,\t548\n4,\t\"CHICKEN MANCHURIAN RECIPE\",\t\"SALT\",\t\"requires: Salt is required for seasoning the marinade mixture.\",\t9.0,\t547\n5,\t\"SALT\",\t\"TUNA RASAM BHAJI RECIPE\",\t\"consumes: Salt is used for seasoning the dish.\",\t8.0,\t547\n6,\t\"SALT\",\t\"SPICY GRILLED PINEAPPLE SALSA\",\t\"consumes: Salt is added for seasoning the salsa.\",\t8.0,\t545\n7,\t\"APPLE VANILLA WHOLE WHEAT PANCAKES\",\t\"SALT\",\t\"consumes: Salt is included to enhance the flavor of the pancakes.\",\t7.0,\t542\n8,\t\"FRUIT PACHADI\",\t\"SALT\",\t\"consumes: Salt is added for flavoring in the Fruit Pachadi.\",\t7.0,\t542\n9,\t\"CALICUT PAYYOLI CHICKEN FRY\",\t\"SALT\",\t\"consumes: Salt is used in the marination for flavor enhancement.\",\t7.0,\t542\n10,\t\"CHARRED CORN AND RADISH SALAD\",\t\"SALT\",\t\"consumes: Salt is included in the dressing ingredients.\",\t8.0,\t541\n11,\t\"HEALTHY OATS WAFFLES\",\t\"SALT\",\t\"consumes: Salt is included as an ingredient in Healthy Oats Waffles.\",\t7.0,\t541\n12,\t\"CHAMADUMPA SABZI\",\t\"SALT\",\t\"consumes: Salt is added to enhance flavor during the cooking process.\",\t8.0,\t539\n13,\t\"SALT\",\t\"STEAMED CHICKEN WITH SALAD\",\t\"consumes: Salt is used separately to enhance flavors.\",\t6.0,\t539\n14,\t\"GARLIC\",\t\"INDIAN\",\t\"is-labeled-as: Garlic is widely used in Indian cooking to enhance flavor.\"<\",\t8.5,\t438\n15,\t\"GARLIC\",\t\"MIXED VEGETABLE HANDI\",\t\"requires: The recipe requires garlic for flavor.\",\t8.0,\t304\n16,\t\"GARLIC\",\t\"SPICY PRESSURE COOKER MUTTON CURRY\",\t\"consumes: Garlic is part of the onion paste for the curry.\",\t7.0,\t295\n17,\t\"DRIED OREGANO\",\t\"GARLIC\",\t\"consumes: Garlic is typically used with dried oregano for seasoning.\",\t7.0,\t295\n18,\t\"GARLIC\",\t\"KERALA STYLE MUTTON PEPPER FRY\",\t\"consumes: Garlic is used with onion in the sautéing step.\",\t7.0,\t293\n19,\t\"CHICKEN MANCHURIAN RECIPE\",\t\"GARLIC\",\t\"requires: Garlic is required for flavor in the gravy.\",\t9.0,\t292\n20,\t\"GARLIC\",\t\"HEALTHY GENERAL TSO'S CHICKEN\",\t\"consumes: Garlic is included in the sauté for flavor.\",\t8.0,\t290\n21,\t\"CALICUT PAYYOLI CHICKEN FRY\",\t\"GARLIC\",\t\"consumes: Garlic is included in the marination of the chicken.\",\t8.0,\t287\n22,\t\"CHAMADUMPA SABZI\",\t\"GARLIC\",\t\"consumes: Garlic is an ingredient in the ground masala used in the recipe.\",\t8.0,\t284\n23,\t\"INDIAN CHINESE RECIPES\",\t\"INDIAN\",\t\"is-a-part-of: Indian Chinese cuisine is a fusion, representing a unique blend within Indian culinary styles.\",\t8.0,\t205\n24,\t\"INDIAN\",\t\"SPICY PRESSURE COOKER MUTTON CURRY\",\t\"part-of: The recipe falls under Indian cuisine.\",\t8.0,\t201\n25,\t\"CHICKEN MANCHURIAN RECIPE\",\t\"PREPARATION TIME: 15 M\",\t\"time-for: The total preparation time for the recipe is labeled as 15 minutes.\",\t7.0,\t136\n26,\t\"PREPARATION TIME: 15 M\",\t\"TUNA RASAM BHAJI RECIPE\",\t\"time-for: Duration stated for preparation of the dish.\",\t7.0,\t136\n27,\t\"CALICUT PAYYOLI CHICKEN FRY\",\t\"PREPARATION TIME: 15 M\",\t\"time-for: Preparation time indicates how long marination takes.\",\t7.0,\t131\n28,\t\"CHAMADUMPA SABZI\",\t\"PREPARATION TIME: 15 M\",\t\"time-for: Labeled preparation duration for the dish.\",\t7.0,\t128\n29,\t\"DRIED OREGANO\",\t\"PAN\",\t\"uses: Oregano flakes are sprinkled at the end in the pan.\",\t8.0,\t126\n30,\t\"KERALA STYLE MUTTON PEPPER FRY\",\t\"PAN\",\t\"uses: A pan is necessary for frying the mutton and other ingredients.\",\t9.0,\t124\n31,\t\"FRUIT PACHADI\",\t\"PAN\",\t\"uses: A pan is used to heat and combine ingredients.\",\t9.0,\t118\n32,\t\"CALICUT PAYYOLI CHICKEN FRY\",\t\"PAN\",\t\"uses: A pan is used to fry the marinated chicken.\",\t9.0,\t118\n33,\t\"CHICKEN MANCHURIAN RECIPE\",\t\"INDIAN CHINESE RECIPES\",\t\"part-of: It is part of Indian Chinese recipe collection.\",\t8.0,\t59\n34,\t\"MIXING BOWL\",\t\"MIXING BOWL\",\t\"uses: The same bowl is used to prepare both the dumplings and the gravy.\",\t6.0,\t58\n35,\t\"HEALTHY GENERAL TSO'S CHICKEN\",\t\"INDIAN CHINESE RECIPES\",\t\"part-of: This dish falls under Indian Chinese recipes category.\",\t9.0,\t57\n36,\t\"CHICKEN MANCHURIAN RECIPE\",\t\"MIXING BOWL\",\t\"uses: Mixing bowl is used to combine egg, corn flour, and other ingredients.\",\t9.0,\t55\n37,\t\"MIXING BOWL\",\t\"SPICY GRILLED PINEAPPLE SALSA\",\t\"uses: Mixing bowl is needed to combine ingredients.\",\t9.0,\t53\n38,\t\"DRIED OREGANO\",\t\"MIXED VEGETABLES\",\t\"consumes: Dried oregano is mixed with the vegetables for flavor.\",\t7.0,\t51\n39,\t\"CHARRED CORN AND RADISH SALAD\",\t\"MIXING BOWL\",\t\"uses: A mixing bowl is needed to combine the ingredients.\",\t8.0,\t49\n40,\t\"MIXED VEGETABLES\",\t\"TUNA RASAM BHAJI RECIPE\",\t\"consumes: Mixed vegetables contribute to the overall texture and flavor.\",\t8.0,\t48\n41,\t\"SPICY GRILLED PINEAPPLE SALSA\",\t\"SPICY GRILLED PINEAPPLE SALSA\",\t\"alternative-to: This is a possible alternative recipe for a Mexican salsa.\",\t5.0,\t48\n42,\t\"FUSION\",\t\"TUNA RASAM BHAJI RECIPE\",\t\"method-for: Dish is categorized under fusion cuisine.\",\t8.0,\t36\n43,\t\"MEAT MASALA\",\t\"SPICY PRESSURE COOKER MUTTON CURRY\",\t\"consumes: Meat masala is a spice blend used for flavoring the mutton.\",\t7.0,\t31\n44,\t\"CHARRED CORN AND RADISH SALAD\",\t\"FUSION\",\t\"method-for: The salad is part of the Fusion cuisine.\",\t9.0,\t30\n45,\t\"KERALA STYLE MUTTON PEPPER FRY\",\t\"MIX\",\t\"uses: Mixing is performed to combine ingredients thoroughly during cooking.\",\t7.0,\t29\n46,\t\"HEALTHY GENERAL TSO'S CHICKEN\",\t\"SAUCE MIXTURE\",\t\"produces: The sauce mixture is added to the chicken for flavoring.\",\t8.0,\t25\n47,\t\"FRUIT PACHADI\",\t\"MIXED FRUITS\",\t\"consumes: Mixed fruits are used in the preparation of Fruit Pachadi.\",\t9.0,\t23\n48,\t\"CALICUT PAYYOLI CHICKEN FRY\",\t\"MIX WELL\",\t\"part-of: Mixing well is a necessary step for marination.\",\t8.0,\t23\n49,\t\"CALICUT PAYYOLI CHICKEN FRY\",\t\"MEAT MASALA\",\t\"consumes: Meat masala is mixed with the marinated chicken for extra seasoning.\",\t7.0,\t23\n50,\t\"APPLE VANILLA WHOLE WHEAT PANCAKES\",\t\"MIXED FRUITS\",\t\"consumes: Mixed fruits are offered as a topping for serving.\",\t6.0,\t23\n51,\t\"HEALTHY OATS WAFFLES\",\t\"MIX WELL\",\t\"requires: Mixing is a step in the preparation process for Healthy Oats Waffles.\",\t7.0,\t22\n52,\t\"STEAMED CHICKEN WITH SALAD\",\t\"WORLD RECIPES\",\t\"part-of: This recipe belongs to the world cuisine category.\",\t8.0,\t19\n53,\t\"CHAMADUMPA SABZI\",\t\"MIXIE JAR\",\t\"uses: A mixie jar is utilized to grind the spices into a masala.\",\t8.0,\t19\n```\n-----Detail Entity Information-----\n```csv\n\"id\",\t\"entity\",\t\"type\",\t\"description\",\t\"rank\"\n0,\t\"WORLD RECIPES\",\t\"CATEGORY\",\t\"General classification of recipes from multiple regions.\",\t1\n1,\t\"MIX\",\t\"METHOD\",\t\"To combine ingredients thoroughly.\",\t2\n2,\t\"MIXED VEGETABLES\",\t\"INGREDIENT\",\t\"A combination of assorted vegetables used in the recipe.\"<SEP>\"A combination of various chopped vegetables.\"<SEP>\"A combination of various seasonal vegetables used in the dish.\"<SEP>\"A combination of various vegetables used in the dish.\"<SEP>\"A combination of vegetables used for variety and nutrition.\"<SEP>\"A variety of chopped vegetables used in the recipe.\"<SEP>\"A variety of vegetables combined for cooking.\"<SEP>\"Assorted vegetables used in the recipe.\"<SEP>\"Combination of various chopped vegetables used as filling.\",\t22\n```\n-----Source Documents-----\n```csv\n\"id\",\t\"content\"\n0,\t\"Recipe: Steamed Chicken With Salad Recipe .\nCuisine: Continental. Course: Appetizer. Diet type: High Protein Non Vegetarian.\nCategory: World Recipes. Preparation Time: 10 M. Cooking Time: 30 M.\nIngredients: Chicken breasts, Black pepper powder, Salt, Cabbage (Patta Gobi/ Muttaikose), Carrot (Gajjar), Red Bell pepper (Capsicum), Whole Egg, Coriander (Dhania) Leaves, Fresh orange juice, Extra Virgin Olive Oil, Salt and Pepper.\nInstructions: To begin making the Steamed Chicken with Salad Recipe, we will keep the vegetable steamer on. Marinate the chicken with salt and pepper and keep it inside the steamer to steam for at least 25 minutes. Keep all the vegetables cut and ready to make the salad. In a separate bowl whisk in the dressing ingredients which includes orange juice, olive oil, salt and pepper and keep it ready. Pour some over the vegetable and toss it well, keep some to glaze the chicken. Once the chicken is steamed, slice them and glaze the chicken pieces with the reaming of the dressing mixture. To serve place the salad first over a serving plate, place the glazed chicken pieces and also slice the egg and keep it to the side. Sprinkle some seasoning if you on top.  Serve the Steamed Chicken with Salad Recipe on its own with   for a healthy protein rich meal..\nSummary: This recipe belongs to the Continental cuisine and is typically served as Appetizer.\nIt is a high protein non vegetarian dish that uses Chicken breasts, Black pepper powder, Salt among other ingredients.\nReference: https://www.archanaskitchen.com/steamed-chicken-with-salad-recipe\"\n1,\t\"Recipe: Kerala Style Mutton Pepper Fry Recipe.\nCuisine: Kerala Recipes. Course: Appetizer. Diet type: Non Vegeterian.\nCategory: Mutton Recipes. Preparation Time: 10 M. Cooking Time: 60 M.\nIngredients: Mutton, Cumin powder (Jeera), Red Chilli powder, Coriander Powder (Dhania), Turmeric powder (Haldi), Salt, Lemon juice, Onion, Garlic, Ginger, Curry leaves, Black pepper powder, Fresh coconut, Salt, Water, Coconut Oil.\nInstructions: To begin making the Kerala Style Mutton Pepper Fry recipe, wash mutton pieces well and marinate it with all the spices mentioned in the list. Heat coconut oil in a pan. Add garlic and ginger pieces. Fry for 1 minute. Add finely chopped onions and curry leaves. Cook till onions turn soft. Add marinated mutton and 3/4 teaspoon salt. Add pepper powder, coconut pieces, mix well. Continue to cook for 4 minutes. Add 2 cups water and mix well. Cover and let it cook until mutton gets cooked well and water is fully evaporated. Kerala style mutton sukka/fry is ready. Kerala Style Mutton Pepper Fry as a side dish along with   and   for a weekday dinner with family..\nSummary: This recipe belongs to the Kerala Recipes cuisine and is typically served as Appetizer.\nIt is a non vegeterian dish that uses Mutton, Cumin powder (Jeera), Red Chilli powder among other ingredients.\nReference: https://www.archanaskitchen.com/kerala-mutton-pepper-fry-recipe\"\n2,\t\"Recipe: Mulakootal (Vegetables In Coconut Gravy) Recipe.\nCuisine: South Indian Recipes. Course: Lunch. Diet type: Vegetarian.\nCategory: Indian Curry Recipes. Preparation Time: 15 M. Cooking Time: 30 M.\nIngredients: Mixed vegetables, Arhar dal (Split Toor Dal), Turmeric powder (Haldi), Fresh coconut, White Urad Dal (Split), Mustard seeds (Rai/ Kadugu), Dry Red Chillies, Cumin seeds (Jeera), Coconut Oil, Mustard seeds (Rai/ Kadugu), Dry Red Chillies, Curry leaves.\nInstructions: To begin making the Mulakootal recipe, firstly wash, peel and dice all vegetables. You can use any vegetables you have at home. I like to use vegetables like carrot, lauki, drumstick, beans, potato, white pumpkin and cauliflower. In a large pot (use an earthen pot if you have, the flavour is lovely)or in a  , boil all the vegetables with little water with salt and turmeric. In an another  , boil the toor dal and keep it aside. Dry roast all the ingredients for the paste apart from coconut for 2-3 minutes till fragrant and slight brown. Grind together coconut and the roasted spices to a smooth paste adding little water if required. Add the toor dal and coconut paste to the boiled vegetables and let it simmer further for 5 minutes till the flavours have blended and the raw smell of coconut has gone. In a small  , heat coconut oil and add mustard seeds, red chilly and curry leaves and sauté for 2 minutes. Pour this over the curry and it is ready to be served. Serve Mulakootal with hot steamed rice for a perfect summer lunch..\nSummary: This recipe belongs to the South Indian Recipes cuisine and is typically served as Lunch.\nIt is a vegetarian dish that uses Mixed vegetables, Arhar dal (Split Toor Dal), Turmeric powder (Haldi) among other ingredients.\nReference: https://www.archanaskitchen.com/mulakootal-vegetables-in-coconut-gravy-recipe\"\n3,\t\"Recipe: Open Bean and Veggies Burrito Muffin Recipe.\nCuisine: Mexican. Course: Appetizer. Diet type: Vegetarian.\nCategory: Continental Party Appetizer & Starter Recipes. Preparation Time: 10 M. Cooking Time: 8 M.\nIngredients: Mixed vegetables, Pickled Jalapenos, Red Chilli flakes, Dried oregano, Cooked rice, Rajma (Large Kidney Beans), Salt and Pepper, Lemon juice, Parsley leaves, Cheese, Spring Onion Greens.\nInstructions: To begin making Open Bean and Veggies Burrito Muffin Recipe, boil the kidney beans with 1 cup of water in a pressure cooker with salt for about 6 whistle and set aside to release the pressure naturally.  Steam all the vegetables in a vegetable steamer for 10 minutes and keep it ready.  Mix together boiled rice, steamed vegetables, jalapeños, red chilli flakes, oregano, kidney beans and tomato salsa. Add salt, lemon juice and pepper as required. Keep the stuffing as dry as possible. Do a taste check and adjust spices. Preheat the oven at 200 degrees C for about 7-8 minutes. Meanwhile, take one half of the tortilla, roll it and place in a muffin tray. Add 2 spoonfuls of the stuffing. With the weight of the stuffing, the rolled up tortilla will hold its shape. Use up the rest of the five halved tortillas into the muffin pan and distribute the stuffing in all six. Then sprinkle cheese, parsley and spring onions on top. Now brush the sides of each tortilla with some oil to get it to crisp up and turn golden brown while baking. Bake Burrito Muffin in a preheated oven at 200 degree C for about 7-8 minutes or until they are sufficiently golden and cheese has melted. Serve Open Bean and Veggies Burrito Muffin Recipe with fresh  , Sour Cream or   if you need to avoid dairy products..\nSummary: This recipe belongs to the Mexican cuisine and is typically served as Appetizer.\nIt is a vegetarian dish that uses Mixed vegetables, Pickled Jalapenos, Red Chilli flakes among other ingredients.\nReference: https://www.archanaskitchen.com/open-bean-and-veggies-burrito-muffin-recipe\"\n4,\t\"Recipe: Karnataka Special Huli Tovve Recipe.\nCuisine: Kerala Recipes. Course: Lunch. Diet type: Vegetarian.\nCategory: Indian Curry Recipes. Preparation Time: 10 M. Cooking Time: 30 M.\nIngredients: Mixed vegetables, Raw Peanuts (Moongphali), Arhar dal (Split Toor Dal), Salt, Jaggery, Fresh coconut, Dry Red Chillies, Chana dal (Bengal Gram Dal), White Urad Dal (Split), Cinnamon Stick (Dalchini), Oil, Mustard seeds (Rai/ Kadugu), Asafoetida (hing), Curry leaves.\nInstructions: To begin with Huli Tovve, wash and soak the toor dal till you prepare your vegetables. Wash and cut the vegetables. Pressure cook Toor dal, mixed vegetables and peanuts till they the  releases 3-4 whistles. The next step is to prepare the paste. Dry roast urad dal, chana dal, cinnamon and red chilli separately till they turn light gold. Add coconut to this and grind all of this into a smooth paste. Remove the lid after the cooker cools down. Add the ground paste to this and 2 cups of water, salt and jaggery and boil. Boil till the hulitovve thickens on high flame. For tempering, heat the oil in a  . Add mustard seeds and let it crackle. Add red chilly and curry leaves. Once they crisp up, add it to the hulitovve. Serve Huli Tovve with hot steamed rice and  ..\nSummary: This recipe belongs to the Kerala Recipes cuisine and is typically served as Lunch.\nIt is a vegetarian dish that uses Mixed vegetables, Raw Peanuts (Moongphali), Arhar dal (Split Toor Dal) among other ingredients.\nReference: https://www.archanaskitchen.com/karnataka-special-huli-tovve-recipe\"\n5,\t\"Recipe: Mint Vegetables Moilee Recipe (Mixed Vegetables Cooked In Minty Coconut Milk).\nCuisine: Kerala Recipes. Course: Lunch. Diet type: Vegetarian.\nCategory: Indian Curry Recipes. Preparation Time: 15 M. Cooking Time: 20 M.\nIngredients: Mixed vegetables, Onion, Tomato, Green Chilli, Ginger, Garlic, Curry leaves, Coconut milk, Coconut milk, Mustard seeds, Black pepper powder, Sunflower Oil, Coconut Oil, Lemon juice, Mint Leaves (Pudina), Salt.\nInstructions: To begin making the Mint Vegetables Moilee recipe, scrape the coconut and extract the thick and thin coconut milk and keep aside. Heat oil in a , once heated add the mustard seeds and let it splutter. Add the curry leaves and the thinly sliced onions and sauté till it gets translucent. Add the ginger and the sliced garlic pods and cook until the raw smell evaporates. Add the cubes vegetables, pepper powder and turmeric powder, and sauté for a minute. Add the thin coconut milk and let the vegetables cook with the lid on. This will take 5 to 6 minutes. Add the chopped tomatoes and let it cook for a minute. Once the vegetables are cooked, add the thick coconut milk and the mint paste and heat it for 2 minutes. Make sure you don't bring this mix to a boil at this stage else the coconut milk the curdle. Switch off the flame, season with salt and add the lemon juice. Serve the Mint Vegetables Moilee Recipe with   or   or Steamed Rice for Sunday brunch..\nSummary: This recipe belongs to the Kerala Recipes cuisine and is typically served as Lunch.\nIt is a vegetarian dish that uses Mixed vegetables, Onion, Tomato among other ingredients.\nReference: https://www.archanaskitchen.com/mint-vegetables-moilee-recipe-mixed-vegetables-cooked-in-minty-coconut-milk\"\n6,\t\"Recipe: Goan Vegetable Curry Recipe.\nCuisine: Goan Recipes. Course: Lunch. Diet type: Vegetarian.\nCategory: Indian Curry Recipes. Preparation Time: 15 M. Cooking Time: 20 M.\nIngredients: Mixed vegetables, Onion, Salt, Turmeric powder (Haldi), Green Chilli, Coconut Oil, Fresh coconut, Kashmiri dry red chillies, Whole Black Peppercorns, Onion, Garlic, Coriander (Dhania) Seeds, Cumin seeds (Jeera), Tamarind.\nInstructions: To begin making the Goan Vegetable Curry Recipe, clean and chop the vegetables into cubes.  Add oil in a heavy bottomed pan and add onions. Cook till the onions becomes translucent. Add remaining vegetables, turmeric powder, green chillies and required amount of water. Cook on medium flame till it is done. Meanwhile, grind all the ingredients mentioned under masala including coconut, kashmiri dry red chillies, whole black peppercorns, onion, garlic, coriander seeds, cumin seeds, tamarind to a smooth paste.  Add the masala paste and salt to the cooked vegetables. Cook on sim till the raw smell from curry goes and keep stirring in between. This will take about 5 to 7 minutes. Switch off when the curry is cooked properly. Serve hot. Serve Goan Vegetable Curry Recipe along with  and   for a weekday meal..\nSummary: This recipe belongs to the Goan Recipes cuisine and is typically served as Lunch.\nIt is a vegetarian dish that uses Mixed vegetables, Onion, Salt among other ingredients.\nReference: https://www.archanaskitchen.com/goan-vegetable-curry-recipe\"\n7,\t\"Recipe: Tuna Rasam Bhaji Recipe (Tuna Sabzi Flavoured With Rasam Powder).\nCuisine: Fusion. Course: Side Dish. Diet type: High Protein Non Vegetarian.\nCategory: Rasam Recipes. Preparation Time: 15 M. Cooking Time: 15 M.\nIngredients: Canned tuna, Onion, Tomato, Green Bell Pepper (Capsicum), Potato (Aloo), Carrot (Gajjar), Green Chillies, Ginger, Rasam Powder, Turmeric powder (Haldi), Red Chilli powder, Cumin seeds (Jeera), Lemon, Salt, Coriander (Dhania) Leaves, Sunflower Oil, Mixed vegetables.\nInstructions: To begin making Tuna Rasam Bhaji Recipe (Tuna Sabzi Flavoured With Rasam Powder), prepare the vegetables and drain the tuna from the can. Heat 1-2 teaspoons of oil in a large pan or kadai. Once the oil is hot, add Jeera, allow them to sizzle. Immediately after they start sizzling, add julienned ginger and slit green chillies and fry for about 10 seconds. Add the onions and fry on low-medium heat until they turn translucent and soft. Add the turmeric powder, chilli powder (optional), rasam powder and sauté. Add the remaining vegetables and fry for 2-3 minutes or until the veggies are cooked about halfway through. Add the canned tuna and mix until the masala has coated the fish. Adjust the salt and cook for about 8-10 minutes with covered lid, stirring every once in a while, avoiding any charring. Once done and the tuna is cooked, squeeze in the fresh lemon juice and garnish with coriander leaves and julienned ginger. Serve Tuna Rasam Bhaji Recipe (Tuna Sabzi Flavoured With Rasam Powder) with  , and  , rice with  ..\nSummary: This recipe belongs to the Fusion cuisine and is typically served as Side Dish.\nIt is a high protein non vegetarian dish that uses Canned tuna, Onion, Tomato among other ingredients.\nReference: https://www.archanaskitchen.com/tuna-rasam-bhaji-recipe-tuna-sabzi-flavoured-with-rasam-powder\"\n8,\t\"Recipe: Vegetarian Sago Dumpling Recipe.\nCuisine: Thai. Course: Snack. Diet type: Vegetarian.\nCategory: Indian Chinese Recipes. Preparation Time: 40 M. Cooking Time: 25 M.\nIngredients: Sabudana (Tapioca Pearls), Shallots, Mixed vegetables, Coriander (Dhania) Leaves, Coriander (Dhania) Leaves, Black pepper powder, Garlic, Oil, Water, Garlic, Oil.\nInstructions: To begin making the Vegetarian Sago Dumpling Recipe, first soak sago/tapioca pearls in 1/2 cup of  hot water till the sago turns translucent. Remember not to over-soak the pearls, else, the dough turns soggy. Mince garlic, cilantro leaves. You can take a couple of cilantro roots as well. Add finely chopped onion and mix together. Put a  Kadai/wok on medium flame and heat oil. Add the minced mixture, saute until the onion turn translucent and soft. Once the onions are soft, add finely chopped cabbage, carrot and beans. Stir well to combine. Next add soy sauce and pepper powder. Saute till all the ingredients are combined well. Turn off the heat. Keep aside and let the filling cool down completely. Meanwhile, take all the soaked sago in a bowl after draining water, wet you hands thoroughly, knead for 2 - 3 minutes until very pliable. Wet your  hands and take a small amount of dough, flatten and make a disc shape of around 6 cm. Place 1 teaspoon of the vegetable filling in the center, then close the flattened disc carefully and shape into a round ball. Keep the ball on a lightly greased plate. Repeat the process with the remaining dough and the filling. Now ready the steamer for cooking these balls. Before placing the balls in the steamer, brush the steamer plate with oil. Steam them for 15 minutes or till the sago becomes soft and transparent. The time required for steaming might vary upon the thickness of the wrapping. Meanwhile, prepare the garlic oil by heating oil in a tadka pan and add crushed garlic to it. Saute the garlic until brown and turn off the heat. Remove the garlic from the oil. The garlic oil is ready. Remove the Vegetarian Sago Dumpling from the steamer once the tapioca covering is soft and translucent by dipping a spoon into the oil in order to prevent the dumplings from sticking to the spoon. Brush each dumpling with garlic oil. Garnish with fresh cilantro and serve hot. Serve Vegetarian Sago Dumpling Recipe during evening, along with with drizzled garlic oil and soy sauce for snack or as a side with   to make a meal..\nSummary: This recipe belongs to the Thai cuisine and is typically served as Snack.\nIt is a vegetarian dish that uses Sabudana (Tapioca Pearls), Shallots, Mixed vegetables among other ingredients.\nReference: https://www.archanaskitchen.com/vegetarian-sago-dumpling-recipe\"\n9,\t\"Recipe: Mushroom Cutlet Vegetarian Sizzler Recipe.\nCuisine: Continental. Course: Main Course. Diet type: Vegetarian.\nCategory: Continental Food Recipes. Preparation Time: 30 M. Cooking Time: 45 M.\nIngredients: Mixed vegetables, Cabbage (Patta Gobi/ Muttaikose), Salt, Black pepper powder, Sunflower Oil, Cooked rice, Garlic, Black pepper powder, Chilli vinegar, Salt, Sunflower Oil, Potatoes (Aloo), Button mushrooms, Salt, Red Chilli powder, Whole Wheat Bread crumbs, Sunflower Oil, Sunflower Oil, Black pepper powder, Garlic, Chilli vinegar, Tomato Ketchup, Water.\nInstructions: To begin making the Mushroom Cutlet Vegetarian Sizzler Recipe we will make all the individual dishes first and keep them ready. Into a mixing bowl add the boiled potatoes and mash them well. Keep aside. Heat oil in a kadai. Add finely chopped mushrooms and saute until mushrooms are well cooked and all the water has evaporated from the mushrooms. Turn off the heat and allow the mushrooms to cool.  Add the cooled mushrooms to the mashed potatoes along with chili powder, salt and mix well to combine. Make equal sized balls and flatten it into a round to make the cutlet. Coat the mushroom cutlets in breadcrumbs on both sides and keep them aside. Add enough oil to a preheated pan and shallow fry the mushroom cutlets till golden brown on both sides.  Cook rice  in a pressure cooker and keep aside to cool completely. Follow   to cook rice. Heat oil in a wok. Add finely chopped garlic and saute for few seconds, then add the cooked rice and toss. Next add vinegar, soy sauce, pepper powder, salt to taste and toss well to combine. Cut vegetables of your choice like carrots, beans, capsicum or broccoli into chunks. Heat oil in a pan, add the vegetables, salt and pepper powder and saute on high heat for a minute or two until the vegetables have softened a bit. There should still be a bite to the vegetables.  Remove from heat and keep aside. Heat oil in a kadai. Add minced garlic and saute until raw smell goes off. Do not brown the garlic. Add chili sauce, soy sauce, vinegar, ketchup, pepper powder and stir quickly to combine. Turn off the heat. Heat the sizzling iron plate to red hot, be careful while doing this and make sure no kids are present nearby. Once the plate it red hot, remove from heat, sprinkle some water. Place a few leaves of cabbage over it. Spoon fried rice over &  stir fry veggies on the rice and the mushroom cutlets over it. Drizzle some sauce and serve Mushroom Cutlet Vegetarian Sizzler Recipe hot. Serve Mushroom Cutlet Vegetarian Sizzler Recipe as a one dish for weekend dinner along with  ..\nSummary: This recipe belongs to the Continental cuisine and is typically served as Main Course.\nIt is a vegetarian dish that uses Mixed vegetables, Cabbage (Patta Gobi/ Muttaikose), Salt among other ingredients.\nReference: https://www.archanaskitchen.com/mushroom-cutlet-vegetarian-sizzler-recipe\"\n10,\t\"Recipe: Budhha's Delight Recipe (Thin Rice Noodles With Vegetables).\nCuisine: Asian. Course: Dinner. Diet type: Vegetarian.\nCategory: Indian Chinese Recipes. Preparation Time: 20 M. Cooking Time: 15 M.\nIngredients: Tofu, Salt, Black pepper powder, Sesame (Gingelly) Oil, Honey, Ginger, Garlic, Corn flour, Oil, Onions, Baby corn, Bamboo shots, Mixed vegetables, Rice Vermicelli Noodles (Thin).\nInstructions: To begin making the Budhha's Delight recipe, firstly preheat the oven to 250 degrees. Line a pan with foil and place the tofu cubes in a single layer on the  pan. Season it with salt and pepper to taste. Bake for 20 minutes or until lightly browned. You can also saute the tofu pieces in 1 teaspoon oil until brown and collect aside. Heat water in a pan and boil rice noodles, strain and collect the cooked noodles in a bowl and set aside Take a small mixing bowl and add soy sauce, sesame oil, honey, ginger and garlic and mix well. Take the cornstarch and mix with 1/4 cup of cold water and add to the soy sauce mixture and stir well. Heat the oil in a wok and add the vegetables and season with salt and pepper. Saute for 5 minutes, stirring occasionally. Now add 2 tablespoons water to the wok and cook until vegetables are tender. Add in the tofu cubes, baby corn and bamboo shoots. Pour the prepared sauce over the tofu mixture and bring to a boil till sauce thickens. Stir in the rice noodles and and turn off the gas. Garnish with sliced green onions and serve with rice. Serve Budhha's Delight on its own   for a weekend night dinner..\nSummary: This recipe belongs to the Asian cuisine and is typically served as Dinner.\nIt is a vegetarian dish that uses Tofu, Salt, Black pepper powder among other ingredients.\nReference: https://www.archanaskitchen.com/budhha-s-delight-recipe-thin-rice-noodles-with-vegetables\"\n```\n",
  "node_hits": {
    "use_communities": [
      {
        "id": 0,
        "report_string": "# Indian Cuisine Recipes Featuring Garlic and Onion  This community focuses on a variety of Indian recipes, notably those that utilize garlic and onion as foundational ingredients. Key dishes include Dal Shorba, Kaju Butter Masala, and Waffled Falafels and Vegetables, which highlight the importance of these aromatics in enhancing flavors. The interdependence of these dishes is illustrated through shared ingredients, methods, and regional variations, demonstrating a rich cultural heritage.  ## Core ingredients: Garlic and Onion  Garlic and onion are essential components across this community's recipes, serving as aromatics that significantly enhance flavor. These ingredients are foundational to many Indian cuisines and are crucial in the preparation methods typical of the region, such as sautéing, which forms the flavor base for various dishes.  ## Diversity of recipes representing Indian cuisine  The community encompasses a range of Indian culinary styles, illustrated by dishes such as Goan Style Mushroom Vindaloo and Kashmiri Style Rista, each reflecting regional flavors and cooking techniques. The recipes leverage the unique flavor properties of garlic and onion to achieve deep and complex taste profiles characteristic of Indian cooking traditions.  ## Dietary inclusivity with vegetarian options  Several recipes cater to vegetarian diets, showcasing dishes such as Waffled Falafels and Vegetables, Kaju Butter Masala, and soups like Dal Shorba. This dietary consideration enhances the community's relevance to a broader audience, promoting nutritious and diverse meal choices.  ## Interconnected use of ingredients  Relationships reveal interactions between garlic and onion with other ingredients such as cumin, tomatoes, and various spices in recipes. For instance, sauces may combine garlic and onion for a complex flavor backdrop, thereby enriching the overall dish aesthetic and taste.  ## Common cooking methods highlight procedural complexity  The community exhibits a variety of cooking methods including sautéing, simmering, and pressure cooking. Sautéing is frequently employed to prepare garlic and onion, illustrating its importance in building flavor bases for dishes like Kaju Butter Masala and Dal Shorba.  ## Health benefits associated with garlic and onion  Numerous health benefits attributed to garlic and onion, such as anti-inflammatory and antioxidant properties, enhance the appeal of these recipes. Their frequent incorporation not only boosts flavor but also emphasizes overall well-being, positioning the community as not just culinary but also health-oriented.  ## Clear categorization aids in recipe navigation  The recipes are well-categorized by type (e.g., soups, curries) and dietary labels, making it easier for cooks to navigate and select meals based on personal preferences or dietary restrictions. This organization underscores the diversity present in achieving varied culinary outcomes.  ## Cultural significance of meal preparation practices  These recipes often reflect cultural practices surrounding meal preparation, making garlic and onion integral to both festive and daily cooking in Indian households. The connection of these ingredients to traditional practices highlights the cultural richness and adaptability of Indian cuisine.  ## Explicit timing for preparation and cooking  Cooking times for various dishes such as Dal Shorba (10-15 minutes preparation) provide essential scheduling information for cooks, crucial for effective meal planning. Clear timing guidelines foster efficient kitchen management, especially in professional settings."
      },
      {
        "id": 1,
        "report_string": "# Bengali Vegetarian Dishes Featuring Turmeric and Salt  This community features a range of Bengali vegetarian recipes centered around key ingredients such as turmeric powder and salt. Significant entities include popular dishes like 'Bengali Style Kaddu Lobia Ki Sabzi with Panch Phoran Masala' and 'Arbi Jhol'. The relationships highlight the fundamental role of these ingredients in seasoning, flavor enhancement, and the methods of preparation involved in these culturally rich recipes.  ## Core vegetarian recipes with health benefits  The community showcases recipes like 'Bengali Style Kaddu Lobia Ki Sabzi with Panch Phoran Masala' and 'Arbi Jhol', distinguished by their plant-based ingredients. Turmeric powder is a recurring element in these dishes, noted for its health benefits, including its anti-inflammatory properties. Salt is essential as a basic seasoning, used to enhance flavors in almost every recipe, emphasizing its necessity in cooking.  ## Significance of turmeric as a key spice  Turmeric powder (Haldi) plays a vital role across various recipes, such as adding color and depth of flavor to dishes like 'Arbi Jhol'. It is recognized not just for its culinary value but also for its health-enhancing characteristics. Relationships show that turmeric is commonly paired with other spices, which adds both complexity and health benefits, establishing its central role in Bengali vegetarian cooking.  ## Salt's ubiquitous role in flavor enhancement  Throughout the narratives of the recipes, salt is a consistent ingredient required for seasoning. For dishes like 'Bengali Aloo Dum', salt is critical for achieving the proper flavor balance. Additionally, the community outlines various substitutions for salt, suggesting places where lower-sodium options can be used, which reflects a growing concern for health-conscious cooking.  ## Diverse cooking methods showcased  The preparation of these recipes involves various cooking techniques including pressure cooking and sautéing. For instance, dishes like 'Arbi Jhol' utilize pressure cooking to ensure the softness and flavor integration of colocasia. These methods not only enhance the flavor profiles but also cater to the texture preferences typical of Bengali cuisine.  ## Explicit time constraints guide meal planning  Most recipes provide clear preparation and cooking times that enable effective meal planning. For example, 'Bengali Style Kaddu Lobia Ki Sabzi' has a designated prep time of 10 minutes, which helps cooks to streamline their culinary tasks. Incorporating time indicators aids novice cooks in managing their cooking schedules efficiently and accurately.  ## Cultural significance of recipes  The recipes within this community reflect deep-rooted cultural practices and the importance of traditional vegetarian cuisine in Bengali culture. By focusing on dishes that utilize local and seasonal ingredients like pumpkin and black-eyed beans, these recipes emphasize cultural heritage while promoting inclusive dietary options.  ## Dietary classifications support vegetarian practices  Many dishes are classified as vegetarian, making them suitable for those adhering strictly to plant-based diets. Labels of 'vegetarian' or explicit references to dietary guidelines help consumers make informed choices, showcasing the community's commitment to catering to diverse dietary preferences."
      },
      {
        "id": 2,
        "report_string": "# Diverse Indian Curry Recipes Featuring Green Chillies  This community encapsulates a variety of Indian curry recipes that prominently feature green chillies as a key ingredient. Significant entities include several regional recipes such as Kerala Style Mutton Pepper Fry, Bengali Aloo Dum, Coorg Style Kumbala Curry, and Malwani Pumpkin and Raw Mango Curry. Key relationships highlight the usage of ingredients, methods of cooking, preparation and cooking times, as well as dietary classifications.  ## Variety of Recipes Representing Different Regions  The community consists of an array of dishes rooted in various Indian cuisines, including Kerala, Bengali, Coorg, and Malvani. Notable recipes include Kerala Style Mutton Pepper Fry, which features mutton and spices, and Bengali Aloo Dum, focusing on baby potatoes and spices. Each recipe represents the unique features and flavors associated with its regional culinary tradition.  ## Green Chillies as a Central Ingredient  Green chillies are a common ingredient across multiple recipes, known for providing heat and enhancing flavor. They are featured in recipes like Green Chilli Vegetable and many curry preparations where they serve as the primary source of spice. Their widespread use emphasizes the importance of balancing heat in these dishes to cater to different palates.  ## Specific Preparation and Cooking Times  Several recipes specify their preparation and cooking times, ensuring that cooks can plan accordingly. For example, the preparation for Kerala Style Mutton Pepper Fry requires 10 minutes, while cooking takes around 50 minutes. These explicit time frames guide the cooking process effectively, making it easier to manage multiple dishes simultaneously.  ## Dietary Classifications and Suitability  Many of the recipes are categorized as vegetarian or non-vegetarian, catering to diverse dietary needs. Dishes like Coorg Style Kumbala Curry and Dahi Wale Tinda Ki Sabzi are classified as vegetarian, while Kerala Style Mutton Pepper Fry is a non-vegetarian dish, allowing users to choose based on their dietary preferences.  ## Common Usage of Salt in Flavors  Salt appears consistently in the recipes, identified as a crucial element for flavor enhancement. For instance, it is necessary in Bengali Aloo Dum and Kerala Style Mutton Pepper Fry. The relationships establish a recurring requirement for salt to ensure that the dishes achieve appropriate taste profiles.  ## Cooking Techniques and Methods  The methodologies adopted in these recipes vary from sautéing and cooking to grinding spices. Techniques like 'Heat' and 'Stir' are fundamental in preparing these dishes, reflecting general cooking methodologies commonly used across Indian recipes. The importance of these methods is evident in how they influence the texture and flavor of the final dish.  ## Ingredients and Complementary Spices  The recipes share a variety of ingredients that enhance their profiles, including turmeric, garlic, and various spices like fennel and coriander. These spices not only complement the green chillies but also reinforce the culinary tradition of layering flavors within these dishes, showcasing the complexity of Indian cuisine.  ## Tools and Appliances Used  Different recipes highlight the tools required for preparation and cooking, such as non-stick woks, kadais, and heavy-bottomed pans used in these curries. The choice of cooking equipment plays a significant role in the cooking technique and helps achieve desired results, ensuring better management of heat when preparing dishes.  ## Serving Suggestions and Accompaniments  Many recipes include serving suggestions, such as pairing with rice or chapati. For instance, dishes like Cucumber Mor Kuzhambu are suggested to be served with steamed rice, providing guidance on how best to enjoy the flavors. This aspect enriches the dining experience by complementing the main dishes."
      },
      {
        "id": 3,
        "report_string": "# Kerala Style Mutton Pepper Fry — Mutton Recipe  This community centers around the 'Kerala Style Mutton Pepper Fry' recipe, highlighting key ingredients like mutton and a diverse range of spices. It employs essential cooking methods including marinating and frying, with explicit mentions of preparation and cooking times. Furthermore, it identifies the dish as a part of both Kerala recipes and as a non-vegetarian appetizer.  ## Core ingredients and spices  The recipe prominently features mutton as the main ingredient, supplemented by a rich mix of spices including garlic, ginger, turmeric, and red chili powder. Their inclusion is critical for flavor development and showcases the traditional essence of Kerala cuisine.  ## Methodology of preparation  This dish involves essential cooking steps: marinating the mutton with spices and frying the mixture. The act of marinating ensures that the flavors deeply penetrate the meat, while frying is integral to create a desirable texture and aroma.  ## Preparation and cooking time specifications  The recipe outlines 'Preparation Time: 10 minutes' and 'Cooking Time: 60 minutes.' This structured time allocation is significant for cooks to manage their cooking process effectively and ensure the dish is prepared within the expected timeframe.  ## Non-vegetarian classification and serving style  The dish is categorized as a non-vegetarian appetizer, which holds cultural significance within Kerala cuisine. This classification informs cooks about its position within meal planning and dietary preferences.  ## Diverse cooking techniques employed  Techniques such as frying and mixing play a crucial role in the cooking process. Effective frying is necessary to enhance flavors and achieve proper doneness, while thorough mixing of ingredients ensures even seasoning and texture."
      },
      {
        "id": 4,
        "report_string": "# Broccoli-Centric Recipes — Vegetarian Cuisine  This community revolves around recipes primarily involving broccoli, including soups and stir-fries. Key entities include various broccoli-based recipes, associated ingredients like paneer and horse gram, and various cooking tools like woks and soup pots. The overarching dietary theme is vegetarianism, with clear emphasis on nutrition, preparation times, and cooking methods.  ## Key Recipes Highlighted  The community includes notable recipes such as 'Protein Rich Paneer and Horse Gram Soup', 'Light and Creamy Broccoli Soup', and 'Chinese Style Sweet and Spicy Broccoli Stir Fry with Sausage'. Each recipe emphasizes various cooking methods and ingredients, suggesting a diverse culinary approach focusing on the nutritional benefits of broccoli.  ## Diverse Ingredient Profiles  The recipes incorporate a rich array of ingredients including broccoli, mixed vegetables, paneer, and various spices. Broccoli serves as a foundational element across different dishes, while complementary ingredients like horse gram dal and paneer enhance protein content in vegetarian meals.  ## Emphasis on Preparation and Cooking Times  Each recipe comes with specified preparation and cooking times, as seen in 'Chinese Style Sweet and Spicy Broccoli Stir Fry with Sausage' which has a labeled prep time of 10 minutes, indicating a focus on efficient meal preparation for cooks.  ## Vegetarian Dietary Compliance  The recipes are predominately vegetarian, as evidenced by the 'method-for' relationships stating that the 'Light and Creamy Broccoli Soup' adheres to vegetarian dietary requirements. This aligns well with the community's theme of promoting health-conscious cooking.  ## Cooking Techniques and Tool Utilization  Various cooking techniques such as sautéing, steaming, and using pressure cookers are prevalent in the recipes. Tools like the non-stick pan, soup pot, and handy traditional vessels enhance cooking versatility, indicating the importance of methodical preparation in achieving texture and flavor.  ## Nutritional Value Focus  Broccoli serves not only as the primary ingredient but as a nutritional keystone throughout the recipes. The incorporation of high-protein ingredients alongside broccoli highlights a conscious effort to bolster the nutritional profile of vegetarian meals for optimal health benefits.  ## Regional and Culinary Influences  The community includes recipes that draw from various culinary influences such as Indian and Chinese cuisines, seen in dishes like 'Chinese Style Sweet and Spicy Broccoli Stir Fry'. This mix showcases the versatility of broccoli in diverse recipes while adding complexity to the community’s culinary identity.  ## Seasoning and Flavoring Complexity  The use of various spices including turmeric, garlic, and chili powders indicates a layered approach to flavoring the dishes. Seasoning ingredients enhance the taste profile, contributing to the unique appeal of each recipe while enhancing the overall sensory experience.  ## Role of Mixed Vegetables  Several recipes feature mixed vegetables, which enrich the nutritional value and flavor profile of the primary broccoli dishes. This approach not only adds variety but also appeals to a broader range of dietary preferences, creating meals that are both colorful and nutritious."
      },
      {
        "id": 5,
        "report_string": "# Steamed Chicken with Salad (Continental, Appetizer)  This community revolves around a dish of steamed chicken served with a fresh salad, incorporating a variety of ingredients like vegetables and dressings. Key relationships include the use of a vegetable steamer for preparation and the categorization of the dish under continental cuisine and as an appetizer. Notable ingredients consumed are chicken breasts, various vegetables, and seasonings, with explicit preparation and cooking time noted.  ## Core dish composition and method  The recipe consists of steamed chicken breasts served alongside a mixed vegetable salad. It highlights both the steaming technique and the combination of fresh ingredients that enhance flavor, showing a clear link between the use of the vegetable steamer and the meal's preparation.  ## Ingredients and tools involved  Key ingredients include chicken breasts for the protein, various salad vegetables such as cabbage, carrots, and red bell peppers, and additional flavoring components like coriander leaves and olive oil. The vegetable steamer is essential for preparing the chicken and vegetables, emphasizing the need for proper tool usage in the cooking process.  ## Diet and cuisine classification  The dish is categorized under continental cuisine and categorized as an appetizer. It fits within the high-protein non-vegetarian diet category, highlighting its appeal to specific dietary preferences and its versatile serving options.  ## Explicit time constraints for preparation and cooking  Preparation time is noted as 10 minutes, while cooking takes about 30 minutes. These time constraints help in planning and executing the dish effectively, ensuring that cooks are aware of the total time commitment required for meal preparation.  ## Versatile use of seasonings and dressings  The dish utilizes several seasonings and dressings, such as salt, pepper, and fresh orange juice, contributing to a flavorful experience. The use of these ingredients is critical for enhancing the overall taste of the dish while also providing different health benefits."
      },
      {
        "id": 6,
        "report_string": "# Vegetarian Global Cuisine: Smoked Spanish Rice & Varied Salads  This community encompasses several vegetarian recipes, highlighting the Smoked Vegetarian Spanish Rice as a central dish. It incorporates key ingredients such as red bell pepper, cabbage, and basmati rice, along with various methods and tools. Its relationships indicate the dietary suitability (vegetarian), preparation durations, and notable cooking techniques, such as smoking. Recipes range from appetizers to main courses, each with specific ingredient interactions and preparation instructions.  ## Diverse range of vegetarian recipes  The community includes varied vegetarian recipes such as Smoked Vegetarian Spanish Rice, Cabbage, Bell Pepper and Apples with Sriracha Slaw, and Steamed Chicken with Salad. Each recipe presents unique combinations of ingredients and preparation techniques suitable for vegetarian diets, emphasizing the versatility of fruits, vegetables, and grains.  ## Key ingredients with significant culinary roles  Ingredients like red bell pepper, basmati rice, and cabbage are integral to multiple recipes. Red bell pepper appears prominently as a sweetening and colorful agent in dishes like Slaw and Spanish Rice. Basmati rice serves as a foundational element in recipes including the vegetarian Spanish rice, highlighting its role in various cuisines.  ## Explicit time constraints for recipes  Preparation and cooking durations are specified for several recipes, such as 10 minutes preparation time and 30 minutes cooking time for Smoked Vegetarian Spanish Rice. These time entities are critical for planning cooking sessions and managing schedules for meal preparation.  ## Cooking methods that enhance flavor  The use of unique methods such as smoking, sautéing, and steaming are prevalent across the recipes. For instance, Smoked Vegetarian Spanish Rice employs the smoking method to infuse it with smokiness, while the slaw utilizes sautéing to highlight flavor enhancement with ingredients like garlic and onions.  ## Varied nutritional profiles across dishes  The inclusion of diverse ingredients in the recipes ensures a broad range of nutrients. For example, the rice dish incorporates vegetables and spices, while the salads add protein sources through items like chickpeas, showcasing the community's ability to cater to nutritional needs.  ## Labeling and dietary suitability highlighted  Several recipes are explicitly labeled as 'vegetarian,' underlining their suitability for vegetarian diets. For instance, the Smoked Vegetarian Spanish Rice and the Cabbage, Bell Pepper and Apples with Sriracha Slaw are confirmed vegetarians, aligning these recipes with dietary claims.  ## Tools and equipment essential for preparation  Key tools such as bowls, pans, and a vegetable steamer are necessary for executing the recipes. For instance, the bowl is crucial for mixing ingredients in various salads and dressings, indicating the communal nature of preparing these dishes and the importance of having the right kitchenware.  ## Cross-referencing with cultural cuisines  The dishes reflect a blend of cultural influences, such as the Spanish traditional aspects seen in the smoked rice and the modern interpretations present in the slaw. The categorization under the 'world recipes' and 'continental' further elaborates on the community's diverse culinary landscape."
      },
      {
        "id": 7,
        "report_string": "# Vegetable Mix Community — Nutrition and Flavor  The community focuses on mixed vegetables and their connections with various recipes and ingredients. The key ingredients include carrot, beans, cauliflower, lauki, and white pumpkin, all of which contribute to a variety of dishes. The relationships reveal that these vegetables are often utilized together in meals, providing nutrition and enhancing flavor.  ## Diverse ingredient usage  Mixed vegetables consist of a variety of chopped vegetables, which are integral to numerous recipes, including 'Tuna Rasam Bhaji', 'Goan Vegetable Curry', and 'Mulakootal'. This indicates a versatile usage across different cuisines, providing nutritional value and variety.  ## Key vegetable relationships  Among the mixed vegetables, components like carrots and beans are noted for their specific contributions to dishes. Carrots add sweetness and crunch, while beans contribute texture and nutrition. The relationships show how these fundamental ingredients work together in many recipes.  ## Common usage in signature dishes  Mixed vegetables are featured prominently in several dishes like 'Vegetarian Sago Dumpling' and 'Moroccan Harira', indicating their role in providing essential flavors and components. Recipes that utilize mixed vegetables capitalize on their combined textures and tastes to enhance overall dish quality.  ## Cooking methods  Several relationships highlight that mixed vegetables are often steamed, as indicated by their connection to the 'Vegetable Steamer'. This method preserves nutrients while ensuring the vegetables are cooked to an appropriate tenderness for consumption.  ## Flavor-enhancing ingredients  The addition of flavorings such as turmeric powder, lemon juice, and dried oregano alongside mixed vegetables amplifies the overall taste profile of dishes. This emphasizes the importance of seasoning in the culinary context of mixed vegetables."
      }
    ],
    "use_reasoning_path": [
      {
        "src_tgt": [
          "INDIAN",
          "SALT"
        ],
        "description": "is-labeled-as: Salt is a basic ingredient in Indian cooking, essential for flavor.<\"",
        "weight": 7.5
      },
      {
        "src_tgt": [
          "MIXED VEGETABLE HANDI",
          "SALT"
        ],
        "description": "requires: The recipe requires salt for seasoning.",
        "weight": 9.0
      },
      {
        "src_tgt": [
          "SALT",
          "SPICY PRESSURE COOKER MUTTON CURRY"
        ],
        "description": "consumes: Salt is used to enhance the flavor of the mutton.",
        "weight": 8.0
      },
      {
        "src_tgt": [
          "KERALA STYLE MUTTON PEPPER FRY",
          "SALT"
        ],
        "description": "consumes: Salt is used to enhance the flavors during cooking. substitutes-for: Salt is also mentioned twice, but as a general ingredient, it's still relevant.",
        "weight": 12.0
      },
      {
        "src_tgt": [
          "CHICKEN MANCHURIAN RECIPE",
          "SALT"
        ],
        "description": "requires: Salt is required for seasoning the marinade mixture.",
        "weight": 9.0
      },
      {
        "src_tgt": [
          "SALT",
          "TUNA RASAM BHAJI RECIPE"
        ],
        "description": "consumes: Salt is used for seasoning the dish.",
        "weight": 8.0
      },
      {
        "src_tgt": [
          "SALT",
          "SPICY GRILLED PINEAPPLE SALSA"
        ],
        "description": "consumes: Salt is added for seasoning the salsa.",
        "weight": 8.0
      },
      {
        "src_tgt": [
          "APPLE VANILLA WHOLE WHEAT PANCAKES",
          "SALT"
        ],
        "description": "consumes: Salt is included to enhance the flavor of the pancakes.",
        "weight": 7.0
      },
      {
        "src_tgt": [
          "FRUIT PACHADI",
          "SALT"
        ],
        "description": "consumes: Salt is added for flavoring in the Fruit Pachadi.",
        "weight": 7.0
      },
      {
        "src_tgt": [
          "CALICUT PAYYOLI CHICKEN FRY",
          "SALT"
        ],
        "description": "consumes: Salt is used in the marination for flavor enhancement.",
        "weight": 7.0
      },
      {
        "src_tgt": [
          "CHARRED CORN AND RADISH SALAD",
          "SALT"
        ],
        "description": "consumes: Salt is included in the dressing ingredients.",
        "weight": 8.0
      },
      {
        "src_tgt": [
          "HEALTHY OATS WAFFLES",
          "SALT"
        ],
        "description": "consumes: Salt is included as an ingredient in Healthy Oats Waffles.",
        "weight": 7.0
      },
      {
        "src_tgt": [
          "CHAMADUMPA SABZI",
          "SALT"
        ],
        "description": "consumes: Salt is added to enhance flavor during the cooking process.",
        "weight": 8.0
      },
      {
        "src_tgt": [
          "SALT",
          "STEAMED CHICKEN WITH SALAD"
        ],
        "description": "consumes: Salt is used separately to enhance flavors.",
        "weight": 6.0
      },
      {
        "src_tgt": [
          "GARLIC",
          "INDIAN"
        ],
        "description": "is-labeled-as: Garlic is widely used in Indian cooking to enhance flavor.<\"",
        "weight": 8.5
      },
      {
        "src_tgt": [
          "GARLIC",
          "MIXED VEGETABLE HANDI"
        ],
        "description": "requires: The recipe requires garlic for flavor.",
        "weight": 8.0
      },
      {
        "src_tgt": [
          "GARLIC",
          "SPICY PRESSURE COOKER MUTTON CURRY"
        ],
        "description": "consumes: Garlic is part of the onion paste for the curry.",
        "weight": 7.0
      },
      {
        "src_tgt": [
          "DRIED OREGANO",
          "GARLIC"
        ],
        "description": "consumes: Garlic is typically used with dried oregano for seasoning.",
        "weight": 7.0
      },
      {
        "src_tgt": [
          "GARLIC",
          "KERALA STYLE MUTTON PEPPER FRY"
        ],
        "description": "consumes: Garlic is used with onion in the sautéing step.",
        "weight": 7.0
      },
      {
        "src_tgt": [
          "CHICKEN MANCHURIAN RECIPE",
          "GARLIC"
        ],
        "description": "requires: Garlic is required for flavor in the gravy.",
        "weight": 9.0
      },
      {
        "src_tgt": [
          "GARLIC",
          "HEALTHY GENERAL TSO'S CHICKEN"
        ],
        "description": "consumes: Garlic is included in the sauté for flavor.",
        "weight": 8.0
      },
      {
        "src_tgt": [
          "CALICUT PAYYOLI CHICKEN FRY",
          "GARLIC"
        ],
        "description": "consumes: Garlic is included in the marination of the chicken.",
        "weight": 8.0
      },
      {
        "src_tgt": [
          "CHAMADUMPA SABZI",
          "GARLIC"
        ],
        "description": "consumes: Garlic is an ingredient in the ground masala used in the recipe.",
        "weight": 8.0
      },
      {
        "src_tgt": [
          "INDIAN CHINESE RECIPES",
          "INDIAN"
        ],
        "description": "is-a-part-of: Indian Chinese cuisine is a fusion, representing a unique blend within Indian culinary styles.",
        "weight": 8.0
      },
      {
        "src_tgt": [
          "INDIAN",
          "SPICY PRESSURE COOKER MUTTON CURRY"
        ],
        "description": "part-of: The recipe falls under Indian cuisine.",
        "weight": 8.0
      },
      {
        "src_tgt": [
          "CHICKEN MANCHURIAN RECIPE",
          "PREPARATION TIME: 15 M"
        ],
        "description": "time-for: The total preparation time for the recipe is labeled as 15 minutes.",
        "weight": 7.0
      },
      {
        "src_tgt": [
          "PREPARATION TIME: 15 M",
          "TUNA RASAM BHAJI RECIPE"
        ],
        "description": "time-for: Duration stated for preparation of the dish.",
        "weight": 7.0
      },
      {
        "src_tgt": [
          "CALICUT PAYYOLI CHICKEN FRY",
          "PREPARATION TIME: 15 M"
        ],
        "description": "time-for: Preparation time indicates how long marination takes.",
        "weight": 7.0
      },
      {
        "src_tgt": [
          "CHAMADUMPA SABZI",
          "PREPARATION TIME: 15 M"
        ],
        "description": "time-for: Labeled preparation duration for the dish.",
        "weight": 7.0
      },
      {
        "src_tgt": [
          "DRIED OREGANO",
          "PAN"
        ],
        "description": "uses: Oregano flakes are sprinkled at the end in the pan.",
        "weight": 8.0
      },
      {
        "src_tgt": [
          "KERALA STYLE MUTTON PEPPER FRY",
          "PAN"
        ],
        "description": "uses: A pan is necessary for frying the mutton and other ingredients.",
        "weight": 9.0
      },
      {
        "src_tgt": [
          "FRUIT PACHADI",
          "PAN"
        ],
        "description": "uses: A pan is used to heat and combine ingredients.",
        "weight": 9.0
      },
      {
        "src_tgt": [
          "CALICUT PAYYOLI CHICKEN FRY",
          "PAN"
        ],
        "description": "uses: A pan is used to fry the marinated chicken.",
        "weight": 9.0
      },
      {
        "src_tgt": [
          "CHICKEN MANCHURIAN RECIPE",
          "INDIAN CHINESE RECIPES"
        ],
        "description": "part-of: It is part of Indian Chinese recipe collection.",
        "weight": 8.0
      },
      {
        "src_tgt": [
          "MIXING BOWL",
          "MIXING BOWL"
        ],
        "description": "uses: The same bowl is used to prepare both the dumplings and the gravy.",
        "weight": 6.0
      },
      {
        "src_tgt": [
          "HEALTHY GENERAL TSO'S CHICKEN",
          "INDIAN CHINESE RECIPES"
        ],
        "description": "part-of: This dish falls under Indian Chinese recipes category.",
        "weight": 9.0
      },
      {
        "src_tgt": [
          "CHICKEN MANCHURIAN RECIPE",
          "MIXING BOWL"
        ],
        "description": "uses: Mixing bowl is used to combine egg, corn flour, and other ingredients.",
        "weight": 9.0
      },
      {
        "src_tgt": [
          "MIXING BOWL",
          "SPICY GRILLED PINEAPPLE SALSA"
        ],
        "description": "uses: Mixing bowl is needed to combine ingredients.",
        "weight": 9.0
      },
      {
        "src_tgt": [
          "DRIED OREGANO",
          "MIXED VEGETABLES"
        ],
        "description": "consumes: Dried oregano is mixed with the vegetables for flavor.",
        "weight": 7.0
      },
      {
        "src_tgt": [
          "CHARRED CORN AND RADISH SALAD",
          "MIXING BOWL"
        ],
        "description": "uses: A mixing bowl is needed to combine the ingredients.",
        "weight": 8.0
      },
      {
        "src_tgt": [
          "MIXED VEGETABLES",
          "TUNA RASAM BHAJI RECIPE"
        ],
        "description": "consumes: Mixed vegetables contribute to the overall texture and flavor.",
        "weight": 8.0
      },
      {
        "src_tgt": [
          "SPICY GRILLED PINEAPPLE SALSA",
          "SPICY GRILLED PINEAPPLE SALSA"
        ],
        "description": "alternative-to: This is a possible alternative recipe for a Mexican salsa.",
        "weight": 5.0
      },
      {
        "src_tgt": [
          "FUSION",
          "TUNA RASAM BHAJI RECIPE"
        ],
        "description": "method-for: Dish is categorized under fusion cuisine.",
        "weight": 8.0
      },
      {
        "src_tgt": [
          "MEAT MASALA",
          "SPICY PRESSURE COOKER MUTTON CURRY"
        ],
        "description": "consumes: Meat masala is a spice blend used for flavoring the mutton.",
        "weight": 7.0
      },
      {
        "src_tgt": [
          "CHARRED CORN AND RADISH SALAD",
          "FUSION"
        ],
        "description": "method-for: The salad is part of the Fusion cuisine.",
        "weight": 9.0
      },
      {
        "src_tgt": [
          "KERALA STYLE MUTTON PEPPER FRY",
          "MIX"
        ],
        "description": "uses: Mixing is performed to combine ingredients thoroughly during cooking.",
        "weight": 7.0
      },
      {
        "src_tgt": [
          "HEALTHY GENERAL TSO'S CHICKEN",
          "SAUCE MIXTURE"
        ],
        "description": "produces: The sauce mixture is added to the chicken for flavoring.",
        "weight": 8.0
      },
      {
        "src_tgt": [
          "FRUIT PACHADI",
          "MIXED FRUITS"
        ],
        "description": "consumes: Mixed fruits are used in the preparation of Fruit Pachadi.",
        "weight": 9.0
      },
      {
        "src_tgt": [
          "CALICUT PAYYOLI CHICKEN FRY",
          "MIX WELL"
        ],
        "description": "part-of: Mixing well is a necessary step for marination.",
        "weight": 8.0
      },
      {
        "src_tgt": [
          "CALICUT PAYYOLI CHICKEN FRY",
          "MEAT MASALA"
        ],
        "description": "consumes: Meat masala is mixed with the marinated chicken for extra seasoning.",
        "weight": 7.0
      },
      {
        "src_tgt": [
          "APPLE VANILLA WHOLE WHEAT PANCAKES",
          "MIXED FRUITS"
        ],
        "description": "consumes: Mixed fruits are offered as a topping for serving.",
        "weight": 6.0
      },
      {
        "src_tgt": [
          "HEALTHY OATS WAFFLES",
          "MIX WELL"
        ],
        "description": "requires: Mixing is a step in the preparation process for Healthy Oats Waffles.",
        "weight": 7.0
      },
      {
        "src_tgt": [
          "STEAMED CHICKEN WITH SALAD",
          "WORLD RECIPES"
        ],
        "description": "part-of: This recipe belongs to the world cuisine category.",
        "weight": 8.0
      },
      {
        "src_tgt": [
          "CHAMADUMPA SABZI",
          "MIXIE JAR"
        ],
        "description": "uses: A mixie jar is utilized to grind the spices into a masala.",
        "weight": 8.0
      }
    ],
    "node_datas": [
      {
        "entity_name": "WORLD RECIPES",
        "entity_type": "CATEGORY",
        "description": "General classification of recipes from multiple regions.",
        "rank": 1
      },
      {
        "entity_name": "MIX",
        "entity_type": "METHOD",
        "description": "To combine ingredients thoroughly.",
        "rank": 2
      },
      {
        "entity_name": "MIXED VEGETABLES",
        "entity_type": "INGREDIENT",
        "description": "A combination of assorted vegetables used in the recipe. A combination of various chopped vegetables. A combination of various seasonal vegetables used in the dish. A combination of various vegetables used in the dish. A combination of vegetables used for variety and nutrition. A variety of chopped vegetables used in the recipe. A variety of vegetables combined for cooking. Assorted vegetables used in the recipe. Combination of various chopped vegetables used as filling.",
        "rank": 22
      }
    ],
    "use_text_units": [
      {
        "id": 0,
        "content": "Recipe: Steamed Chicken With Salad Recipe .\nCuisine: Continental. Course: Appetizer. Diet type: High Protein Non Vegetarian.\nCategory: World Recipes. Preparation Time: 10 M. Cooking Time: 30 M.\nIngredients: Chicken breasts, Black pepper powder, Salt, Cabbage (Patta Gobi/ Muttaikose), Carrot (Gajjar), Red Bell pepper (Capsicum), Whole Egg, Coriander (Dhania) Leaves, Fresh orange juice, Extra Virgin Olive Oil, Salt and Pepper.\nInstructions: To begin making the Steamed Chicken with Salad Recipe, we will keep the vegetable steamer on. Marinate the chicken with salt and pepper and keep it inside the steamer to steam for at least 25 minutes. Keep all the vegetables cut and ready to make the salad. In a separate bowl whisk in the dressing ingredients which includes orange juice, olive oil, salt and pepper and keep it ready. Pour some over the vegetable and toss it well, keep some to glaze the chicken. Once the chicken is steamed, slice them and glaze the chicken pieces with the reaming of the dressing mixture. To serve place the salad first over a serving plate, place the glazed chicken pieces and also slice the egg and keep it to the side. Sprinkle some seasoning if you on top.  Serve the Steamed Chicken with Salad Recipe on its own with   for a healthy protein rich meal..\nSummary: This recipe belongs to the Continental cuisine and is typically served as Appetizer.\nIt is a high protein non vegetarian dish that uses Chicken breasts, Black pepper powder, Salt among other ingredients.\nReference: https://www.archanaskitchen.com/steamed-chicken-with-salad-recipe"
      },
      {
        "id": 1,
        "content": "Recipe: Kerala Style Mutton Pepper Fry Recipe.\nCuisine: Kerala Recipes. Course: Appetizer. Diet type: Non Vegeterian.\nCategory: Mutton Recipes. Preparation Time: 10 M. Cooking Time: 60 M.\nIngredients: Mutton, Cumin powder (Jeera), Red Chilli powder, Coriander Powder (Dhania), Turmeric powder (Haldi), Salt, Lemon juice, Onion, Garlic, Ginger, Curry leaves, Black pepper powder, Fresh coconut, Salt, Water, Coconut Oil.\nInstructions: To begin making the Kerala Style Mutton Pepper Fry recipe, wash mutton pieces well and marinate it with all the spices mentioned in the list. Heat coconut oil in a pan. Add garlic and ginger pieces. Fry for 1 minute. Add finely chopped onions and curry leaves. Cook till onions turn soft. Add marinated mutton and 3/4 teaspoon salt. Add pepper powder, coconut pieces, mix well. Continue to cook for 4 minutes. Add 2 cups water and mix well. Cover and let it cook until mutton gets cooked well and water is fully evaporated. Kerala style mutton sukka/fry is ready. Kerala Style Mutton Pepper Fry as a side dish along with   and   for a weekday dinner with family..\nSummary: This recipe belongs to the Kerala Recipes cuisine and is typically served as Appetizer.\nIt is a non vegeterian dish that uses Mutton, Cumin powder (Jeera), Red Chilli powder among other ingredients.\nReference: https://www.archanaskitchen.com/kerala-mutton-pepper-fry-recipe"
      },
      {
        "id": 2,
        "content": "Recipe: Mulakootal (Vegetables In Coconut Gravy) Recipe.\nCuisine: South Indian Recipes. Course: Lunch. Diet type: Vegetarian.\nCategory: Indian Curry Recipes. Preparation Time: 15 M. Cooking Time: 30 M.\nIngredients: Mixed vegetables, Arhar dal (Split Toor Dal), Turmeric powder (Haldi), Fresh coconut, White Urad Dal (Split), Mustard seeds (Rai/ Kadugu), Dry Red Chillies, Cumin seeds (Jeera), Coconut Oil, Mustard seeds (Rai/ Kadugu), Dry Red Chillies, Curry leaves.\nInstructions: To begin making the Mulakootal recipe, firstly wash, peel and dice all vegetables. You can use any vegetables you have at home. I like to use vegetables like carrot, lauki, drumstick, beans, potato, white pumpkin and cauliflower. In a large pot (use an earthen pot if you have, the flavour is lovely)or in a  , boil all the vegetables with little water with salt and turmeric. In an another  , boil the toor dal and keep it aside. Dry roast all the ingredients for the paste apart from coconut for 2-3 minutes till fragrant and slight brown. Grind together coconut and the roasted spices to a smooth paste adding little water if required. Add the toor dal and coconut paste to the boiled vegetables and let it simmer further for 5 minutes till the flavours have blended and the raw smell of coconut has gone. In a small  , heat coconut oil and add mustard seeds, red chilly and curry leaves and sauté for 2 minutes. Pour this over the curry and it is ready to be served. Serve Mulakootal with hot steamed rice for a perfect summer lunch..\nSummary: This recipe belongs to the South Indian Recipes cuisine and is typically served as Lunch.\nIt is a vegetarian dish that uses Mixed vegetables, Arhar dal (Split Toor Dal), Turmeric powder (Haldi) among other ingredients.\nReference: https://www.archanaskitchen.com/mulakootal-vegetables-in-coconut-gravy-recipe"
      },
      {
        "id": 3,
        "content": "Recipe: Open Bean and Veggies Burrito Muffin Recipe.\nCuisine: Mexican. Course: Appetizer. Diet type: Vegetarian.\nCategory: Continental Party Appetizer & Starter Recipes. Preparation Time: 10 M. Cooking Time: 8 M.\nIngredients: Mixed vegetables, Pickled Jalapenos, Red Chilli flakes, Dried oregano, Cooked rice, Rajma (Large Kidney Beans), Salt and Pepper, Lemon juice, Parsley leaves, Cheese, Spring Onion Greens.\nInstructions: To begin making Open Bean and Veggies Burrito Muffin Recipe, boil the kidney beans with 1 cup of water in a pressure cooker with salt for about 6 whistle and set aside to release the pressure naturally.  Steam all the vegetables in a vegetable steamer for 10 minutes and keep it ready.  Mix together boiled rice, steamed vegetables, jalapeños, red chilli flakes, oregano, kidney beans and tomato salsa. Add salt, lemon juice and pepper as required. Keep the stuffing as dry as possible. Do a taste check and adjust spices. Preheat the oven at 200 degrees C for about 7-8 minutes. Meanwhile, take one half of the tortilla, roll it and place in a muffin tray. Add 2 spoonfuls of the stuffing. With the weight of the stuffing, the rolled up tortilla will hold its shape. Use up the rest of the five halved tortillas into the muffin pan and distribute the stuffing in all six. Then sprinkle cheese, parsley and spring onions on top. Now brush the sides of each tortilla with some oil to get it to crisp up and turn golden brown while baking. Bake Burrito Muffin in a preheated oven at 200 degree C for about 7-8 minutes or until they are sufficiently golden and cheese has melted. Serve Open Bean and Veggies Burrito Muffin Recipe with fresh  , Sour Cream or   if you need to avoid dairy products..\nSummary: This recipe belongs to the Mexican cuisine and is typically served as Appetizer.\nIt is a vegetarian dish that uses Mixed vegetables, Pickled Jalapenos, Red Chilli flakes among other ingredients.\nReference: https://www.archanaskitchen.com/open-bean-and-veggies-burrito-muffin-recipe"
      },
      {
        "id": 4,
        "content": "Recipe: Karnataka Special Huli Tovve Recipe.\nCuisine: Kerala Recipes. Course: Lunch. Diet type: Vegetarian.\nCategory: Indian Curry Recipes. Preparation Time: 10 M. Cooking Time: 30 M.\nIngredients: Mixed vegetables, Raw Peanuts (Moongphali), Arhar dal (Split Toor Dal), Salt, Jaggery, Fresh coconut, Dry Red Chillies, Chana dal (Bengal Gram Dal), White Urad Dal (Split), Cinnamon Stick (Dalchini), Oil, Mustard seeds (Rai/ Kadugu), Asafoetida (hing), Curry leaves.\nInstructions: To begin with Huli Tovve, wash and soak the toor dal till you prepare your vegetables. Wash and cut the vegetables. Pressure cook Toor dal, mixed vegetables and peanuts till they the  releases 3-4 whistles. The next step is to prepare the paste. Dry roast urad dal, chana dal, cinnamon and red chilli separately till they turn light gold. Add coconut to this and grind all of this into a smooth paste. Remove the lid after the cooker cools down. Add the ground paste to this and 2 cups of water, salt and jaggery and boil. Boil till the hulitovve thickens on high flame. For tempering, heat the oil in a  . Add mustard seeds and let it crackle. Add red chilly and curry leaves. Once they crisp up, add it to the hulitovve. Serve Huli Tovve with hot steamed rice and  ..\nSummary: This recipe belongs to the Kerala Recipes cuisine and is typically served as Lunch.\nIt is a vegetarian dish that uses Mixed vegetables, Raw Peanuts (Moongphali), Arhar dal (Split Toor Dal) among other ingredients.\nReference: https://www.archanaskitchen.com/karnataka-special-huli-tovve-recipe"
      },
      {
        "id": 5,
        "content": "Recipe: Mint Vegetables Moilee Recipe (Mixed Vegetables Cooked In Minty Coconut Milk).\nCuisine: Kerala Recipes. Course: Lunch. Diet type: Vegetarian.\nCategory: Indian Curry Recipes. Preparation Time: 15 M. Cooking Time: 20 M.\nIngredients: Mixed vegetables, Onion, Tomato, Green Chilli, Ginger, Garlic, Curry leaves, Coconut milk, Coconut milk, Mustard seeds, Black pepper powder, Sunflower Oil, Coconut Oil, Lemon juice, Mint Leaves (Pudina), Salt.\nInstructions: To begin making the Mint Vegetables Moilee recipe, scrape the coconut and extract the thick and thin coconut milk and keep aside. Heat oil in a , once heated add the mustard seeds and let it splutter. Add the curry leaves and the thinly sliced onions and sauté till it gets translucent. Add the ginger and the sliced garlic pods and cook until the raw smell evaporates. Add the cubes vegetables, pepper powder and turmeric powder, and sauté for a minute. Add the thin coconut milk and let the vegetables cook with the lid on. This will take 5 to 6 minutes. Add the chopped tomatoes and let it cook for a minute. Once the vegetables are cooked, add the thick coconut milk and the mint paste and heat it for 2 minutes. Make sure you don't bring this mix to a boil at this stage else the coconut milk the curdle. Switch off the flame, season with salt and add the lemon juice. Serve the Mint Vegetables Moilee Recipe with   or   or Steamed Rice for Sunday brunch..\nSummary: This recipe belongs to the Kerala Recipes cuisine and is typically served as Lunch.\nIt is a vegetarian dish that uses Mixed vegetables, Onion, Tomato among other ingredients.\nReference: https://www.archanaskitchen.com/mint-vegetables-moilee-recipe-mixed-vegetables-cooked-in-minty-coconut-milk"
      },
      {
        "id": 6,
        "content": "Recipe: Goan Vegetable Curry Recipe.\nCuisine: Goan Recipes. Course: Lunch. Diet type: Vegetarian.\nCategory: Indian Curry Recipes. Preparation Time: 15 M. Cooking Time: 20 M.\nIngredients: Mixed vegetables, Onion, Salt, Turmeric powder (Haldi), Green Chilli, Coconut Oil, Fresh coconut, Kashmiri dry red chillies, Whole Black Peppercorns, Onion, Garlic, Coriander (Dhania) Seeds, Cumin seeds (Jeera), Tamarind.\nInstructions: To begin making the Goan Vegetable Curry Recipe, clean and chop the vegetables into cubes.  Add oil in a heavy bottomed pan and add onions. Cook till the onions becomes translucent. Add remaining vegetables, turmeric powder, green chillies and required amount of water. Cook on medium flame till it is done. Meanwhile, grind all the ingredients mentioned under masala including coconut, kashmiri dry red chillies, whole black peppercorns, onion, garlic, coriander seeds, cumin seeds, tamarind to a smooth paste.  Add the masala paste and salt to the cooked vegetables. Cook on sim till the raw smell from curry goes and keep stirring in between. This will take about 5 to 7 minutes. Switch off when the curry is cooked properly. Serve hot. Serve Goan Vegetable Curry Recipe along with  and   for a weekday meal..\nSummary: This recipe belongs to the Goan Recipes cuisine and is typically served as Lunch.\nIt is a vegetarian dish that uses Mixed vegetables, Onion, Salt among other ingredients.\nReference: https://www.archanaskitchen.com/goan-vegetable-curry-recipe"
      },
      {
        "id": 7,
        "content": "Recipe: Tuna Rasam Bhaji Recipe (Tuna Sabzi Flavoured With Rasam Powder).\nCuisine: Fusion. Course: Side Dish. Diet type: High Protein Non Vegetarian.\nCategory: Rasam Recipes. Preparation Time: 15 M. Cooking Time: 15 M.\nIngredients: Canned tuna, Onion, Tomato, Green Bell Pepper (Capsicum), Potato (Aloo), Carrot (Gajjar), Green Chillies, Ginger, Rasam Powder, Turmeric powder (Haldi), Red Chilli powder, Cumin seeds (Jeera), Lemon, Salt, Coriander (Dhania) Leaves, Sunflower Oil, Mixed vegetables.\nInstructions: To begin making Tuna Rasam Bhaji Recipe (Tuna Sabzi Flavoured With Rasam Powder), prepare the vegetables and drain the tuna from the can. Heat 1-2 teaspoons of oil in a large pan or kadai. Once the oil is hot, add Jeera, allow them to sizzle. Immediately after they start sizzling, add julienned ginger and slit green chillies and fry for about 10 seconds. Add the onions and fry on low-medium heat until they turn translucent and soft. Add the turmeric powder, chilli powder (optional), rasam powder and sauté. Add the remaining vegetables and fry for 2-3 minutes or until the veggies are cooked about halfway through. Add the canned tuna and mix until the masala has coated the fish. Adjust the salt and cook for about 8-10 minutes with covered lid, stirring every once in a while, avoiding any charring. Once done and the tuna is cooked, squeeze in the fresh lemon juice and garnish with coriander leaves and julienned ginger. Serve Tuna Rasam Bhaji Recipe (Tuna Sabzi Flavoured With Rasam Powder) with  , and  , rice with  ..\nSummary: This recipe belongs to the Fusion cuisine and is typically served as Side Dish.\nIt is a high protein non vegetarian dish that uses Canned tuna, Onion, Tomato among other ingredients.\nReference: https://www.archanaskitchen.com/tuna-rasam-bhaji-recipe-tuna-sabzi-flavoured-with-rasam-powder"
      },
      {
        "id": 8,
        "content": "Recipe: Vegetarian Sago Dumpling Recipe.\nCuisine: Thai. Course: Snack. Diet type: Vegetarian.\nCategory: Indian Chinese Recipes. Preparation Time: 40 M. Cooking Time: 25 M.\nIngredients: Sabudana (Tapioca Pearls), Shallots, Mixed vegetables, Coriander (Dhania) Leaves, Coriander (Dhania) Leaves, Black pepper powder, Garlic, Oil, Water, Garlic, Oil.\nInstructions: To begin making the Vegetarian Sago Dumpling Recipe, first soak sago/tapioca pearls in 1/2 cup of  hot water till the sago turns translucent. Remember not to over-soak the pearls, else, the dough turns soggy. Mince garlic, cilantro leaves. You can take a couple of cilantro roots as well. Add finely chopped onion and mix together. Put a  Kadai/wok on medium flame and heat oil. Add the minced mixture, saute until the onion turn translucent and soft. Once the onions are soft, add finely chopped cabbage, carrot and beans. Stir well to combine. Next add soy sauce and pepper powder. Saute till all the ingredients are combined well. Turn off the heat. Keep aside and let the filling cool down completely. Meanwhile, take all the soaked sago in a bowl after draining water, wet you hands thoroughly, knead for 2 - 3 minutes until very pliable. Wet your  hands and take a small amount of dough, flatten and make a disc shape of around 6 cm. Place 1 teaspoon of the vegetable filling in the center, then close the flattened disc carefully and shape into a round ball. Keep the ball on a lightly greased plate. Repeat the process with the remaining dough and the filling. Now ready the steamer for cooking these balls. Before placing the balls in the steamer, brush the steamer plate with oil. Steam them for 15 minutes or till the sago becomes soft and transparent. The time required for steaming might vary upon the thickness of the wrapping. Meanwhile, prepare the garlic oil by heating oil in a tadka pan and add crushed garlic to it. Saute the garlic until brown and turn off the heat. Remove the garlic from the oil. The garlic oil is ready. Remove the Vegetarian Sago Dumpling from the steamer once the tapioca covering is soft and translucent by dipping a spoon into the oil in order to prevent the dumplings from sticking to the spoon. Brush each dumpling with garlic oil. Garnish with fresh cilantro and serve hot. Serve Vegetarian Sago Dumpling Recipe during evening, along with with drizzled garlic oil and soy sauce for snack or as a side with   to make a meal..\nSummary: This recipe belongs to the Thai cuisine and is typically served as Snack.\nIt is a vegetarian dish that uses Sabudana (Tapioca Pearls), Shallots, Mixed vegetables among other ingredients.\nReference: https://www.archanaskitchen.com/vegetarian-sago-dumpling-recipe"
      },
      {
        "id": 9,
        "content": "Recipe: Mushroom Cutlet Vegetarian Sizzler Recipe.\nCuisine: Continental. Course: Main Course. Diet type: Vegetarian.\nCategory: Continental Food Recipes. Preparation Time: 30 M. Cooking Time: 45 M.\nIngredients: Mixed vegetables, Cabbage (Patta Gobi/ Muttaikose), Salt, Black pepper powder, Sunflower Oil, Cooked rice, Garlic, Black pepper powder, Chilli vinegar, Salt, Sunflower Oil, Potatoes (Aloo), Button mushrooms, Salt, Red Chilli powder, Whole Wheat Bread crumbs, Sunflower Oil, Sunflower Oil, Black pepper powder, Garlic, Chilli vinegar, Tomato Ketchup, Water.\nInstructions: To begin making the Mushroom Cutlet Vegetarian Sizzler Recipe we will make all the individual dishes first and keep them ready. Into a mixing bowl add the boiled potatoes and mash them well. Keep aside. Heat oil in a kadai. Add finely chopped mushrooms and saute until mushrooms are well cooked and all the water has evaporated from the mushrooms. Turn off the heat and allow the mushrooms to cool.  Add the cooled mushrooms to the mashed potatoes along with chili powder, salt and mix well to combine. Make equal sized balls and flatten it into a round to make the cutlet. Coat the mushroom cutlets in breadcrumbs on both sides and keep them aside. Add enough oil to a preheated pan and shallow fry the mushroom cutlets till golden brown on both sides.  Cook rice  in a pressure cooker and keep aside to cool completely. Follow   to cook rice. Heat oil in a wok. Add finely chopped garlic and saute for few seconds, then add the cooked rice and toss. Next add vinegar, soy sauce, pepper powder, salt to taste and toss well to combine. Cut vegetables of your choice like carrots, beans, capsicum or broccoli into chunks. Heat oil in a pan, add the vegetables, salt and pepper powder and saute on high heat for a minute or two until the vegetables have softened a bit. There should still be a bite to the vegetables.  Remove from heat and keep aside. Heat oil in a kadai. Add minced garlic and saute until raw smell goes off. Do not brown the garlic. Add chili sauce, soy sauce, vinegar, ketchup, pepper powder and stir quickly to combine. Turn off the heat. Heat the sizzling iron plate to red hot, be careful while doing this and make sure no kids are present nearby. Once the plate it red hot, remove from heat, sprinkle some water. Place a few leaves of cabbage over it. Spoon fried rice over &  stir fry veggies on the rice and the mushroom cutlets over it. Drizzle some sauce and serve Mushroom Cutlet Vegetarian Sizzler Recipe hot. Serve Mushroom Cutlet Vegetarian Sizzler Recipe as a one dish for weekend dinner along with  ..\nSummary: This recipe belongs to the Continental cuisine and is typically served as Main Course.\nIt is a vegetarian dish that uses Mixed vegetables, Cabbage (Patta Gobi/ Muttaikose), Salt among other ingredients.\nReference: https://www.archanaskitchen.com/mushroom-cutlet-vegetarian-sizzler-recipe"
      },
      {
        "id": 10,
        "content": "Recipe: Budhha's Delight Recipe (Thin Rice Noodles With Vegetables).\nCuisine: Asian. Course: Dinner. Diet type: Vegetarian.\nCategory: Indian Chinese Recipes. Preparation Time: 20 M. Cooking Time: 15 M.\nIngredients: Tofu, Salt, Black pepper powder, Sesame (Gingelly) Oil, Honey, Ginger, Garlic, Corn flour, Oil, Onions, Baby corn, Bamboo shots, Mixed vegetables, Rice Vermicelli Noodles (Thin).\nInstructions: To begin making the Budhha's Delight recipe, firstly preheat the oven to 250 degrees. Line a pan with foil and place the tofu cubes in a single layer on the  pan. Season it with salt and pepper to taste. Bake for 20 minutes or until lightly browned. You can also saute the tofu pieces in 1 teaspoon oil until brown and collect aside. Heat water in a pan and boil rice noodles, strain and collect the cooked noodles in a bowl and set aside Take a small mixing bowl and add soy sauce, sesame oil, honey, ginger and garlic and mix well. Take the cornstarch and mix with 1/4 cup of cold water and add to the soy sauce mixture and stir well. Heat the oil in a wok and add the vegetables and season with salt and pepper. Saute for 5 minutes, stirring occasionally. Now add 2 tablespoons water to the wok and cook until vegetables are tender. Add in the tofu cubes, baby corn and bamboo shoots. Pour the prepared sauce over the tofu mixture and bring to a boil till sauce thickens. Stir in the rice noodles and and turn off the gas. Garnish with sliced green onions and serve with rice. Serve Budhha's Delight on its own   for a weekend night dinner..\nSummary: This recipe belongs to the Asian cuisine and is typically served as Dinner.\nIt is a vegetarian dish that uses Tofu, Salt, Black pepper powder among other ingredients.\nReference: https://www.archanaskitchen.com/budhha-s-delight-recipe-thin-rice-noodles-with-vegetables"
      }
    ]
  },
  "answer": "Based on various recipes retrieved from the context, here’s a new recipe that combines elements from different cuisines, including high-protein ingredients, vibrant vegetables, and flavorful spices.\n\n### **Mixed Protein Veggie Bowl**\n\n#### **Cuisine:** Fusion  \n#### **Course:** Main Dish  \n#### **Diet Type:** High Protein, Vegetarian  \n\n---\n\n#### **Preparation Time:** 15 minutes   \n#### **Cooking Time:** 30 minutes   \n\n---\n\n#### **Ingredients:**\n- 1 cup Chicken breasts, diced (or substitute with Tofu for a vegetarian option)\n- 1 cup Mixed vegetables (carrot, beans, red bell pepper, and cabbage)\n- 1 cup Cooked rice (or quinoa for a healthier option)\n- 1 cup Cooked kidney beans (Rajma)\n- 2 tablespoons Olive oil\n- 1 tablespoon Fresh orange juice\n- 1 teaspoon Black pepper powder\n- 1 teaspoon Salt\n- 1 teaspoon Cumin powder (Jeera)\n- 1 teaspoon Turmeric powder\n- 1 teaspoon Garlic, minced\n- 1 tablespoon Chilli flakes (optional, for heat)\n- Fresh coriander (Dhania) leaves for garnish\n\n---\n\n#### **Instructions:**\n\n1. **Prepare Ingredients:** \n   - If using chicken, marinate it with salt, black pepper, and turmeric powder for 10 minutes. If using tofu, press it to remove excess water.\n   - Chop the mixed vegetables into bite-sized pieces.\n\n2. **Cook Protein:**\n   - Heat 1 tablespoon of olive oil in a large pan over medium heat. Add minced garlic and sauté until fragrant.\n   - Add marinated chicken or tofu cubes and cook until golden brown and cooked through (approximately 7-10 minutes for chicken, 5-7 for tofu).\n\n3. **Cook Vegetables:**\n   - In the pan with the protein, add mixed vegetables and cook for another 5 minutes until they are tender yet crisp.\n   - Season the mix with cumin powder, black pepper, and salt.\n\n4. **Combine with Rice:**\n   - Stir in the cooked rice and kidney beans into the pan. Add the remaining tablespoon of olive oil, orange juice, and chilli flakes. Mix well to combine all ingredients.\n\n5. **Serve:**\n   - Transfer the mixed protein veggie bowl to a serving platter.\n   - Garnish with fresh coriander leaves for added flavor and serve hot.\n\n---\n\n### **Serving Suggestions:**\n- Pair the bowl with a side salad or a refreshing cucumber raita for a complete meal.\n- Optionally, drizzle with some extra orange juice just before serving for a citrusy kick.\n\nThis fusion recipe incorporates the freshness of salads, the heartiness of proteins, and vibrant flavors drawn from various cuisines, making it a nutritious and delicious dish. Enjoy!\n\n--- \n\nThis recipe synthesizes components from different meal styles, ensuring a balanced, tasty, and visually appealing dish that resonates with various culinary traditions."
}